{"abstract":[{"text":"Renews the user’s credentials using a refresh token.","type":"text"}],"identifier":{"interfaceLanguage":"swift","url":"doc:\/\/com.auth0.Auth0\/documentation\/Auth0\/Authentication\/renew(withRefreshToken:audience:scope:)-7q6zg"},"hierarchy":{"paths":[["doc:\/\/com.auth0.Auth0\/documentation\/Auth0","doc:\/\/com.auth0.Auth0\/documentation\/Auth0\/Authentication"]]},"seeAlsoSections":[{"identifiers":["https:\/\/auth0.com\/docs\/api\/authentication\/refresh-token\/refresh-token","https:\/\/auth0.com\/docs\/secure\/tokens\/refresh-tokens","doc:\/\/com.auth0.Auth0\/documentation\/Auth0\/RefreshTokens","doc:\/\/com.auth0.Auth0\/documentation\/Auth0\/IDTokenValidation"],"title":"Related Documentation","anchor":"Related-Documentation"}],"sections":[],"primaryContentSections":[{"kind":"declarations","declarations":[{"tokens":[{"kind":"keyword","text":"func"},{"text":" ","kind":"text"},{"text":"renew","kind":"identifier"},{"kind":"text","text":"("},{"kind":"externalParam","text":"withRefreshToken"},{"text":" ","kind":"text"},{"text":"refreshToken","kind":"internalParam"},{"text":": ","kind":"text"},{"text":"String","kind":"typeIdentifier","preciseIdentifier":"s:SS"},{"text":", ","kind":"text"},{"text":"audience","kind":"externalParam"},{"kind":"text","text":": "},{"text":"String","preciseIdentifier":"s:SS","kind":"typeIdentifier"},{"text":"?, ","kind":"text"},{"kind":"externalParam","text":"scope"},{"text":": ","kind":"text"},{"preciseIdentifier":"s:SS","text":"String","kind":"typeIdentifier"},{"text":"?) -> ","kind":"text"},{"kind":"keyword","text":"any"},{"text":" ","kind":"text"},{"preciseIdentifier":"s:5Auth016TokenRequestableP","kind":"typeIdentifier","identifier":"doc:\/\/com.auth0.Auth0\/documentation\/Auth0\/TokenRequestable","text":"TokenRequestable"},{"text":"<","kind":"text"},{"preciseIdentifier":"c:@M@Auth0@objc(cs)A0Credentials","identifier":"doc:\/\/com.auth0.Auth0\/documentation\/Auth0\/Credentials","text":"Credentials","kind":"typeIdentifier"},{"text":", ","kind":"text"},{"preciseIdentifier":"s:5Auth019AuthenticationErrorV","text":"AuthenticationError","kind":"typeIdentifier","identifier":"doc:\/\/com.auth0.Auth0\/documentation\/Auth0\/AuthenticationError"},{"text":">","kind":"text"}],"platforms":["iOS"],"languages":["swift"]}]},{"kind":"parameters","parameters":[{"content":[{"inlineContent":[{"type":"text","text":"The refresh token."}],"type":"paragraph"}],"name":"refreshToken"},{"content":[{"inlineContent":[{"type":"text","text":"Identifier of the API that your application is requesting access to. Currently, only the Auth0 My Account API is supported. Defaults to "},{"type":"codeVoice","code":"nil"},{"type":"text","text":"."}],"type":"paragraph"}],"name":"audience"},{"name":"scope","content":[{"inlineContent":[{"text":"Space-separated list of scope values to request. Defaults to ","type":"text"},{"code":"nil","type":"codeVoice"},{"text":".","type":"text"}],"type":"paragraph"}]}]},{"kind":"content","content":[{"anchor":"return-value","type":"heading","level":2,"text":"Return Value"},{"type":"paragraph","inlineContent":[{"text":"A request that will yield Auth0 user’s credentials.","type":"text"}]}]},{"kind":"content","content":[{"anchor":"Usage","text":"Usage","type":"heading","level":2},{"syntax":"swift","type":"codeListing","code":["Auth0","    .authentication()","    .renew(withRefreshToken: credentials.refreshToken)","    .start { result in","        switch result {","        case .success(let credentials):","            print(\"Obtained new credentials: \\(credentials)\")","        case .failure(let error):","            print(\"Failed with: \\(error)\")","        }","    }"]},{"type":"paragraph","inlineContent":[{"text":"You can request credentials for a specific API by passing its audience value. The default scopes configured for","type":"text"},{"text":" ","type":"text"},{"text":"the API will be granted if you don’t request any specific scopes.","type":"text"}]},{"content":[{"type":"paragraph","inlineContent":[{"type":"text","text":"Currently, only the Auth0 My Account API is supported. Support for other APIs will be added in the future."}]}],"type":"aside","style":"important","name":"Important"},{"syntax":"swift","code":["Auth0","    .authentication()","    .renew(withRefreshToken: credentials.refreshToken,","           audience: \"https:\/\/samples.us.auth0.com\/me\",","           scope: \"create:me:authentication_methods\")","    .start { print($0) }"],"type":"codeListing"},{"name":"Note","type":"aside","content":[{"inlineContent":[{"type":"text","text":"Chain "},{"identifier":"doc:\/\/com.auth0.Auth0\/documentation\/Auth0\/TokenRequest\/validateClaims()","type":"reference","isActive":true},{"text":" before calling ","type":"text"},{"code":"start(_:)","type":"codeVoice"},{"text":" to validate the ID token. See ","type":"text"},{"type":"reference","isActive":true,"identifier":"doc:\/\/com.auth0.Auth0\/documentation\/Auth0\/IDTokenValidation"},{"type":"text","text":"."}],"type":"paragraph"}],"style":"note"}]}],"schemaVersion":{"patch":0,"major":0,"minor":3},"kind":"symbol","variants":[{"paths":["\/documentation\/auth0\/authentication\/renew(withrefreshtoken:audience:scope:)-7q6zg"],"traits":[{"interfaceLanguage":"swift"}]}],"defaultImplementationsSections":[{"title":"Authentication Implementations","identifiers":["doc:\/\/com.auth0.Auth0\/documentation\/Auth0\/Authentication\/renew(withRefreshToken:audience:scope:)-297qa"],"anchor":"Authentication-Implementations"}],"metadata":{"roleHeading":"Instance Method","fragments":[{"text":"func","kind":"keyword"},{"kind":"text","text":" "},{"text":"renew","kind":"identifier"},{"text":"(","kind":"text"},{"text":"withRefreshToken","kind":"externalParam"},{"text":": ","kind":"text"},{"preciseIdentifier":"s:SS","text":"String","kind":"typeIdentifier"},{"kind":"text","text":", "},{"kind":"externalParam","text":"audience"},{"kind":"text","text":": "},{"preciseIdentifier":"s:SS","kind":"typeIdentifier","text":"String"},{"text":"?, ","kind":"text"},{"text":"scope","kind":"externalParam"},{"kind":"text","text":": "},{"preciseIdentifier":"s:SS","text":"String","kind":"typeIdentifier"},{"kind":"text","text":"?) -> "},{"kind":"keyword","text":"any"},{"text":" ","kind":"text"},{"text":"TokenRequestable","kind":"typeIdentifier","preciseIdentifier":"s:5Auth016TokenRequestableP"},{"kind":"text","text":"<"},{"text":"Credentials","preciseIdentifier":"c:@M@Auth0@objc(cs)A0Credentials","kind":"typeIdentifier"},{"text":", ","kind":"text"},{"preciseIdentifier":"s:5Auth019AuthenticationErrorV","kind":"typeIdentifier","text":"AuthenticationError"},{"text":">","kind":"text"}],"externalID":"s:5Auth014AuthenticationP5renew16withRefreshToken8audience5scopeAA0F11Requestable_pAA0B5ErrorV0J4TypeRts_AA11CredentialsC06ResultK0RtsXPSS_SSSgAQtF","required":true,"role":"symbol","symbolKind":"method","modules":[{"name":"Auth0"}],"title":"renew(withRefreshToken:audience:scope:)"},"references":{"doc://com.auth0.Auth0/documentation/Auth0/TokenRequest/validateClaims()":{"title":"validateClaims()","identifier":"doc:\/\/com.auth0.Auth0\/documentation\/Auth0\/TokenRequest\/validateClaims()","role":"symbol","abstract":[{"text":"Enables ID token validation for this request.","type":"text"}],"url":"\/documentation\/auth0\/tokenrequest\/validateclaims()","kind":"symbol","conformance":{"availabilityPrefix":[{"text":"Available when","type":"text"}],"constraints":[{"code":"T","type":"codeVoice"},{"type":"text","text":" conforms to "},{"code":"Sendable","type":"codeVoice"},{"type":"text","text":" and "},{"code":"E","type":"codeVoice"},{"text":" conforms to ","type":"text"},{"type":"codeVoice","code":"Auth0APIError"},{"type":"text","text":"."}],"conformancePrefix":[{"type":"text","text":"Conforms when"}]},"type":"topic","fragments":[{"kind":"keyword","text":"func"},{"kind":"text","text":" "},{"kind":"identifier","text":"validateClaims"},{"kind":"text","text":"() -> "},{"text":"any","kind":"keyword"},{"kind":"text","text":" "},{"preciseIdentifier":"s:5Auth016TokenRequestableP","text":"TokenRequestable","kind":"typeIdentifier"},{"text":"<","kind":"text"},{"text":"T","kind":"typeIdentifier","preciseIdentifier":"s:5Auth012TokenRequestV1Txmfp"},{"text":", ","kind":"text"},{"text":"E","preciseIdentifier":"s:5Auth012TokenRequestV1Eq_mfp","kind":"typeIdentifier"},{"text":">","kind":"text"}]},"https://auth0.com/docs/api/authentication":{"title":"Auth0 Authentication API","url":"https:\/\/auth0.com\/docs\/api\/authentication","type":"link","identifier":"https:\/\/auth0.com\/docs\/api\/authentication","titleInlineContent":[{"text":"Auth0 Authentication API","type":"text"}]},"doc://com.auth0.Auth0/documentation/Auth0":{"url":"\/documentation\/auth0","kind":"symbol","identifier":"doc:\/\/com.auth0.Auth0\/documentation\/Auth0","type":"topic","abstract":[{"type":"text","text":"SDK for Apple platforms."}],"role":"collection","title":"Auth0"},"doc://com.auth0.Auth0/documentation/Auth0/Authentication/renew(withRefreshToken:audience:scope:)-297qa":{"fragments":[{"text":"func","kind":"keyword"},{"kind":"text","text":" "},{"text":"renew","kind":"identifier"},{"text":"(","kind":"text"},{"kind":"externalParam","text":"withRefreshToken"},{"text":": ","kind":"text"},{"kind":"typeIdentifier","text":"String","preciseIdentifier":"s:SS"},{"kind":"text","text":", "},{"text":"audience","kind":"externalParam"},{"text":": ","kind":"text"},{"text":"String","preciseIdentifier":"s:SS","kind":"typeIdentifier"},{"text":"?, ","kind":"text"},{"text":"scope","kind":"externalParam"},{"text":": ","kind":"text"},{"text":"String","kind":"typeIdentifier","preciseIdentifier":"s:SS"},{"text":"?) -> ","kind":"text"},{"text":"any","kind":"keyword"},{"kind":"text","text":" "},{"preciseIdentifier":"s:5Auth016TokenRequestableP","kind":"typeIdentifier","text":"TokenRequestable"},{"text":"<","kind":"text"},{"kind":"typeIdentifier","text":"Credentials","preciseIdentifier":"c:@M@Auth0@objc(cs)A0Credentials"},{"text":", ","kind":"text"},{"text":"AuthenticationError","kind":"typeIdentifier","preciseIdentifier":"s:5Auth019AuthenticationErrorV"},{"text":">","kind":"text"}],"type":"topic","abstract":[{"text":"Renews the user’s credentials using a refresh token.","type":"text"}],"role":"symbol","identifier":"doc:\/\/com.auth0.Auth0\/documentation\/Auth0\/Authentication\/renew(withRefreshToken:audience:scope:)-297qa","kind":"symbol","url":"\/documentation\/auth0\/authentication\/renew(withrefreshtoken:audience:scope:)-297qa","title":"renew(withRefreshToken:audience:scope:)"},"doc://com.auth0.Auth0/documentation/Auth0/Authentication/renew(withRefreshToken:audience:scope:)-7q6zg":{"url":"\/documentation\/auth0\/authentication\/renew(withrefreshtoken:audience:scope:)-7q6zg","fragments":[{"text":"func","kind":"keyword"},{"kind":"text","text":" "},{"kind":"identifier","text":"renew"},{"kind":"text","text":"("},{"text":"withRefreshToken","kind":"externalParam"},{"kind":"text","text":": "},{"preciseIdentifier":"s:SS","kind":"typeIdentifier","text":"String"},{"text":", ","kind":"text"},{"kind":"externalParam","text":"audience"},{"kind":"text","text":": "},{"kind":"typeIdentifier","preciseIdentifier":"s:SS","text":"String"},{"kind":"text","text":"?, "},{"kind":"externalParam","text":"scope"},{"kind":"text","text":": "},{"preciseIdentifier":"s:SS","text":"String","kind":"typeIdentifier"},{"text":"?) -> ","kind":"text"},{"text":"any","kind":"keyword"},{"text":" ","kind":"text"},{"preciseIdentifier":"s:5Auth016TokenRequestableP","text":"TokenRequestable","kind":"typeIdentifier"},{"text":"<","kind":"text"},{"kind":"typeIdentifier","preciseIdentifier":"c:@M@Auth0@objc(cs)A0Credentials","text":"Credentials"},{"text":", ","kind":"text"},{"preciseIdentifier":"s:5Auth019AuthenticationErrorV","text":"AuthenticationError","kind":"typeIdentifier"},{"text":">","kind":"text"}],"kind":"symbol","title":"renew(withRefreshToken:audience:scope:)","role":"symbol","type":"topic","required":true,"defaultImplementations":1,"abstract":[{"type":"text","text":"Renews the user’s credentials using a refresh token."}],"identifier":"doc:\/\/com.auth0.Auth0\/documentation\/Auth0\/Authentication\/renew(withRefreshToken:audience:scope:)-7q6zg"},"doc://com.auth0.Auth0/documentation/Auth0/RefreshTokens":{"identifier":"doc:\/\/com.auth0.Auth0\/documentation\/Auth0\/RefreshTokens","type":"topic","role":"article","kind":"article","title":"Refresh Tokens: Common Errors","abstract":[],"url":"\/documentation\/auth0\/refreshtokens"},"doc://com.auth0.Auth0/documentation/Auth0/IDTokenValidation":{"url":"\/documentation\/auth0\/idtokenvalidation","identifier":"doc:\/\/com.auth0.Auth0\/documentation\/Auth0\/IDTokenValidation","kind":"article","role":"article","title":"ID Token Validation","abstract":[{"text":"Validate ID token claims on credential-returning Authentication API requests.","type":"text"}],"type":"topic"},"doc://com.auth0.Auth0/documentation/Auth0/TokenRequestable":{"type":"topic","role":"symbol","url":"\/documentation\/auth0\/tokenrequestable","fragments":[{"kind":"keyword","text":"protocol"},{"text":" ","kind":"text"},{"text":"TokenRequestable","kind":"identifier"}],"identifier":"doc:\/\/com.auth0.Auth0\/documentation\/Auth0\/TokenRequestable","navigatorTitle":[{"text":"TokenRequestable","kind":"identifier"}],"kind":"symbol","abstract":[{"text":"A request that supports opt-in ID token claim validation via a chainable builder API.","type":"text"}],"title":"TokenRequestable"},"https://auth0.com/docs/api/authentication/refresh-token/refresh-token":{"title":"Authentication API Endpoint","url":"https:\/\/auth0.com\/docs\/api\/authentication\/refresh-token\/refresh-token","type":"link","identifier":"https:\/\/auth0.com\/docs\/api\/authentication\/refresh-token\/refresh-token","titleInlineContent":[{"type":"text","text":"Authentication API Endpoint"}]},"doc://com.auth0.Auth0/documentation/Auth0/AuthenticationError":{"url":"\/documentation\/auth0\/authenticationerror","identifier":"doc:\/\/com.auth0.Auth0\/documentation\/Auth0\/AuthenticationError","kind":"symbol","role":"symbol","fragments":[{"kind":"keyword","text":"struct"},{"text":" ","kind":"text"},{"text":"AuthenticationError","kind":"identifier"}],"title":"AuthenticationError","abstract":[{"text":"Represents an error during a request to the Auth0 Authentication API.","type":"text"}],"type":"topic","navigatorTitle":[{"kind":"identifier","text":"AuthenticationError"}]},"doc://com.auth0.Auth0/documentation/Auth0/Authentication":{"type":"topic","role":"symbol","url":"\/documentation\/auth0\/authentication","fragments":[{"text":"protocol","kind":"keyword"},{"text":" ","kind":"text"},{"text":"Authentication","kind":"identifier"}],"identifier":"doc:\/\/com.auth0.Auth0\/documentation\/Auth0\/Authentication","navigatorTitle":[{"kind":"identifier","text":"Authentication"}],"kind":"symbol","abstract":[{"text":"Client for the ","type":"text"},{"identifier":"https:\/\/auth0.com\/docs\/api\/authentication","type":"reference","isActive":true},{"text":".","type":"text"}],"title":"Authentication"},"https://auth0.com/docs/secure/tokens/refresh-tokens":{"title":"Refresh Tokens","url":"https:\/\/auth0.com\/docs\/secure\/tokens\/refresh-tokens","type":"link","identifier":"https:\/\/auth0.com\/docs\/secure\/tokens\/refresh-tokens","titleInlineContent":[{"text":"Refresh Tokens","type":"text"}]},"doc://com.auth0.Auth0/documentation/Auth0/Credentials":{"type":"topic","role":"symbol","url":"\/documentation\/auth0\/credentials","fragments":[{"text":"class","kind":"keyword"},{"text":" ","kind":"text"},{"text":"Credentials","kind":"identifier"}],"identifier":"doc:\/\/com.auth0.Auth0\/documentation\/Auth0\/Credentials","navigatorTitle":[{"kind":"identifier","text":"Credentials"}],"kind":"symbol","abstract":[{"type":"text","text":"User’s credentials obtained from Auth0."}],"title":"Credentials"}}}