{"hierarchy":{"paths":[[]]},"schemaVersion":{"major":0,"patch":0,"minor":3},"sections":[],"topicSections":[{"generated":true,"title":"Articles","anchor":"Articles","identifiers":["doc:\/\/com.auth0.Auth0\/documentation\/Auth0\/UserAgents","doc:\/\/com.auth0.Auth0\/documentation\/Auth0\/RefreshTokens"]},{"generated":true,"title":"Classes","anchor":"Classes","identifiers":["doc:\/\/com.auth0.Auth0\/documentation\/Auth0\/ActClaim","doc:\/\/com.auth0.Auth0\/documentation\/Auth0\/Credentials","doc:\/\/com.auth0.Auth0\/documentation\/Auth0\/UserPatchAttributes"]},{"generated":true,"title":"Protocols","anchor":"Protocols","identifiers":["doc:\/\/com.auth0.Auth0\/documentation\/Auth0\/Auth0APIError","doc:\/\/com.auth0.Auth0\/documentation\/Auth0\/Auth0Error","doc:\/\/com.auth0.Auth0\/documentation\/Auth0\/Authentication","doc:\/\/com.auth0.Auth0\/documentation\/Auth0\/CredentialsStorage","doc:\/\/com.auth0.Auth0\/documentation\/Auth0\/Loggable","doc:\/\/com.auth0.Auth0\/documentation\/Auth0\/Logger","doc:\/\/com.auth0.Auth0\/documentation\/Auth0\/LoginPasskey","doc:\/\/com.auth0.Auth0\/documentation\/Auth0\/MFAClient","doc:\/\/com.auth0.Auth0\/documentation\/Auth0\/MyAccount","doc:\/\/com.auth0.Auth0\/documentation\/Auth0\/MyAccountAuthenticationMethods","doc:\/\/com.auth0.Auth0\/documentation\/Auth0\/MyAccountClient","doc:\/\/com.auth0.Auth0\/documentation\/Auth0\/NewPasskey","doc:\/\/com.auth0.Auth0\/documentation\/Auth0\/PARAuth","doc:\/\/com.auth0.Auth0\/documentation\/Auth0\/RequestValidator","doc:\/\/com.auth0.Auth0\/documentation\/Auth0\/Requestable","doc:\/\/com.auth0.Auth0\/documentation\/Auth0\/SenderConstraining","doc:\/\/com.auth0.Auth0\/documentation\/Auth0\/SignupPasskey","doc:\/\/com.auth0.Auth0\/documentation\/Auth0\/Trackable","doc:\/\/com.auth0.Auth0\/documentation\/Auth0\/Users","doc:\/\/com.auth0.Auth0\/documentation\/Auth0\/WebAuth","doc:\/\/com.auth0.Auth0\/documentation\/Auth0\/WebAuthUserAgent"]},{"generated":true,"title":"Structures","anchor":"Structures","identifiers":["doc:\/\/com.auth0.Auth0\/documentation\/Auth0\/APICredentials","doc:\/\/com.auth0.Auth0\/documentation\/Auth0\/ActorToken","doc:\/\/com.auth0.Auth0\/documentation\/Auth0\/AuthenticationError","doc:\/\/com.auth0.Auth0\/documentation\/Auth0\/AuthenticationMethod","doc:\/\/com.auth0.Auth0\/documentation\/Auth0\/AuthenticationMethods","doc:\/\/com.auth0.Auth0\/documentation\/Auth0\/Authenticator","doc:\/\/com.auth0.Auth0\/documentation\/Auth0\/AuthorizationCode","doc:\/\/com.auth0.Auth0\/documentation\/Auth0\/Challenge","doc:\/\/com.auth0.Auth0\/documentation\/Auth0\/CredentialsManager","doc:\/\/com.auth0.Auth0\/documentation\/Auth0\/CredentialsManagerError","doc:\/\/com.auth0.Auth0\/documentation\/Auth0\/DPoP","doc:\/\/com.auth0.Auth0\/documentation\/Auth0\/DPoPError","doc:\/\/com.auth0.Auth0\/documentation\/Auth0\/EmailEnrollmentChallenge","doc:\/\/com.auth0.Auth0\/documentation\/Auth0\/Factor","doc:\/\/com.auth0.Auth0\/documentation\/Auth0\/Factors","doc:\/\/com.auth0.Auth0\/documentation\/Auth0\/JWK","doc:\/\/com.auth0.Auth0\/documentation\/Auth0\/JWKS","doc:\/\/com.auth0.Auth0\/documentation\/Auth0\/MFAChallenge","doc:\/\/com.auth0.Auth0\/documentation\/Auth0\/MFAEnrollmentChallenge","doc:\/\/com.auth0.Auth0\/documentation\/Auth0\/MFAFactor","doc:\/\/com.auth0.Auth0\/documentation\/Auth0\/MFARequiredErrorPayload","doc:\/\/com.auth0.Auth0\/documentation\/Auth0\/MFARequirements","doc:\/\/com.auth0.Auth0\/documentation\/Auth0\/MFAVerifyError","doc:\/\/com.auth0.Auth0\/documentation\/Auth0\/ManagementError","doc:\/\/com.auth0.Auth0\/documentation\/Auth0\/MfaChallengeError","doc:\/\/com.auth0.Auth0\/documentation\/Auth0\/MfaEnrollmentError","doc:\/\/com.auth0.Auth0\/documentation\/Auth0\/MfaListAuthenticatorsError","doc:\/\/com.auth0.Auth0\/documentation\/Auth0\/MyAccountError","doc:\/\/com.auth0.Auth0\/documentation\/Auth0\/OTPMFAEnrollmentChallenge","doc:\/\/com.auth0.Auth0\/documentation\/Auth0\/PasskeyAuthenticationMethod","doc:\/\/com.auth0.Auth0\/documentation\/Auth0\/PasskeyCredential","doc:\/\/com.auth0.Auth0\/documentation\/Auth0\/PasskeyEnrollmentChallenge","doc:\/\/com.auth0.Auth0\/documentation\/Auth0\/PasskeyLoginChallenge","doc:\/\/com.auth0.Auth0\/documentation\/Auth0\/PasskeySignupChallenge","doc:\/\/com.auth0.Auth0\/documentation\/Auth0\/PhoneEnrollmentChallenge","doc:\/\/com.auth0.Auth0\/documentation\/Auth0\/PushEnrollmentChallenge","doc:\/\/com.auth0.Auth0\/documentation\/Auth0\/PushMFAEnrollmentChallenge","doc:\/\/com.auth0.Auth0\/documentation\/Auth0\/RecoveryCodeEnrollmentChallenge","doc:\/\/com.auth0.Auth0\/documentation\/Auth0\/Request","doc:\/\/com.auth0.Auth0\/documentation\/Auth0\/SSOCredentials","doc:\/\/com.auth0.Auth0\/documentation\/Auth0\/TOTPEnrollmentChallenge","doc:\/\/com.auth0.Auth0\/documentation\/Auth0\/Telemetry","doc:\/\/com.auth0.Auth0\/documentation\/Auth0\/UserInfo","doc:\/\/com.auth0.Auth0\/documentation\/Auth0\/WebAuthError","doc:\/\/com.auth0.Auth0\/documentation\/Auth0\/WebAuthentication"]},{"generated":true,"title":"Variables","anchor":"Variables","identifiers":["doc:\/\/com.auth0.Auth0\/documentation\/Auth0\/defaultScope"]},{"generated":true,"title":"Functions","anchor":"Functions","identifiers":["doc:\/\/com.auth0.Auth0\/documentation\/Auth0\/authentication(clientId:domain:session:)","doc:\/\/com.auth0.Auth0\/documentation\/Auth0\/authentication(session:bundle:)","doc:\/\/com.auth0.Auth0\/documentation\/Auth0\/authorizeWithRequestUri(bundle:)","doc:\/\/com.auth0.Auth0\/documentation\/Auth0\/authorizeWithRequestUri(clientId:domain:)","doc:\/\/com.auth0.Auth0\/documentation\/Auth0\/mfa(clientId:domain:session:)","doc:\/\/com.auth0.Auth0\/documentation\/Auth0\/mfa(session:bundle:)","doc:\/\/com.auth0.Auth0\/documentation\/Auth0\/myAccount(token:domain:session:)","doc:\/\/com.auth0.Auth0\/documentation\/Auth0\/myAccount(token:session:bundle:)","doc:\/\/com.auth0.Auth0\/documentation\/Auth0\/users(token:domain:session:)","doc:\/\/com.auth0.Auth0\/documentation\/Auth0\/users(token:session:bundle:)","doc:\/\/com.auth0.Auth0\/documentation\/Auth0\/webAuth(clientId:domain:session:)","doc:\/\/com.auth0.Auth0\/documentation\/Auth0\/webAuth(session:bundle:)"]},{"generated":true,"title":"Type Aliases","anchor":"Type-Aliases","identifiers":["doc:\/\/com.auth0.Auth0\/documentation\/Auth0\/AuthenticationResult","doc:\/\/com.auth0.Auth0\/documentation\/Auth0\/CredentialsManagerResult","doc:\/\/com.auth0.Auth0\/documentation\/Auth0\/DatabaseUser","doc:\/\/com.auth0.Auth0\/documentation\/Auth0\/ManagementObject","doc:\/\/com.auth0.Auth0\/documentation\/Auth0\/ManagementResult","doc:\/\/com.auth0.Auth0\/documentation\/Auth0\/MyAccountResult","doc:\/\/com.auth0.Auth0\/documentation\/Auth0\/WebAuthProvider","doc:\/\/com.auth0.Auth0\/documentation\/Auth0\/WebAuthProviderCallback","doc:\/\/com.auth0.Auth0\/documentation\/Auth0\/WebAuthResult"]},{"generated":true,"title":"Enumerations","anchor":"Enumerations","identifiers":["doc:\/\/com.auth0.Auth0\/documentation\/Auth0\/AuthenticationMethodType","doc:\/\/com.auth0.Auth0\/documentation\/Auth0\/BiometricPolicy","doc:\/\/com.auth0.Auth0\/documentation\/Auth0\/PasskeyDeviceType","doc:\/\/com.auth0.Auth0\/documentation\/Auth0\/PasswordlessType","doc:\/\/com.auth0.Auth0\/documentation\/Auth0\/PreferredAuthenticationMethod"]},{"generated":true,"title":"Extended Modules","anchor":"Extended-Modules","identifiers":["doc:\/\/com.auth0.Auth0\/documentation\/Auth0\/AuthenticationServices","doc:\/\/com.auth0.Auth0\/documentation\/Auth0\/CryptoKit","doc:\/\/com.auth0.Auth0\/documentation\/Auth0\/Foundation","doc:\/\/com.auth0.Auth0\/documentation\/Auth0\/SimpleKeychain","doc:\/\/com.auth0.Auth0\/documentation\/Auth0\/Swift"]}],"identifier":{"interfaceLanguage":"swift","url":"doc:\/\/com.auth0.Auth0\/documentation\/Auth0"},"kind":"symbol","abstract":[{"text":"SDK for Apple platforms.","type":"text"}],"variants":[{"traits":[{"interfaceLanguage":"swift"}],"paths":["\/documentation\/auth0"]}],"primaryContentSections":[{"content":[{"text":"Overview","level":2,"anchor":"Overview","type":"heading"},{"items":[{"content":[{"type":"paragraph","inlineContent":[{"isActive":true,"identifier":"doc:\/\/com.auth0.Auth0\/documentation\/Auth0\/WebAuth","type":"reference"},{"text":": Web-based authentication client.","type":"text"}]}]},{"content":[{"type":"paragraph","inlineContent":[{"type":"reference","isActive":true,"identifier":"doc:\/\/com.auth0.Auth0\/documentation\/Auth0\/CredentialsManager"},{"type":"text","text":": Credentials management utility for securely storing and retrieving the user’s credentials from the Keychain."}]}]},{"content":[{"type":"paragraph","inlineContent":[{"identifier":"doc:\/\/com.auth0.Auth0\/documentation\/Auth0\/Authentication","isActive":true,"type":"reference"},{"text":": Client for the ","type":"text"},{"identifier":"https:\/\/auth0.com\/docs\/api\/authentication","isActive":true,"type":"reference"},{"text":".","type":"text"}]}]},{"content":[{"type":"paragraph","inlineContent":[{"identifier":"doc:\/\/com.auth0.Auth0\/documentation\/Auth0\/MyAccount","isActive":true,"type":"reference"},{"text":": Client for the My Account API.","type":"text"}]}]},{"content":[{"inlineContent":[{"type":"reference","isActive":true,"identifier":"doc:\/\/com.auth0.Auth0\/documentation\/Auth0\/Users"},{"type":"text","text":": Client for the Users endpoints of the "},{"type":"reference","isActive":true,"identifier":"https:\/\/auth0.com\/docs\/api\/management\/v2"},{"type":"text","text":"."}],"type":"paragraph"}]}],"type":"unorderedList"}],"kind":"content"}],"metadata":{"title":"Auth0","externalID":"Auth0","modules":[{"name":"Auth0"}],"roleHeading":"Framework","symbolKind":"module","role":"collection"},"references":{"doc://com.auth0.Auth0/documentation/Auth0/Users/patch(_:attributes:)":{"required":true,"kind":"symbol","deprecated":true,"fragments":[{"kind":"keyword","text":"func"},{"kind":"text","text":" "},{"kind":"identifier","text":"patch"},{"kind":"text","text":"("},{"preciseIdentifier":"s:SS","kind":"typeIdentifier","text":"String"},{"kind":"text","text":", "},{"kind":"externalParam","text":"attributes"},{"kind":"text","text":": "},{"preciseIdentifier":"s:5Auth019UserPatchAttributesC","kind":"typeIdentifier","text":"UserPatchAttributes"},{"kind":"text","text":") -> "},{"preciseIdentifier":"s:5Auth07RequestV","kind":"typeIdentifier","text":"Request"},{"kind":"text","text":"<"},{"preciseIdentifier":"s:5Auth016ManagementObjecta","kind":"typeIdentifier","text":"ManagementObject"},{"kind":"text","text":", "},{"preciseIdentifier":"s:5Auth015ManagementErrorV","kind":"typeIdentifier","text":"ManagementError"},{"kind":"text","text":">"}],"identifier":"doc:\/\/com.auth0.Auth0\/documentation\/Auth0\/Users\/patch(_:attributes:)","title":"patch(_:attributes:)","abstract":[{"type":"text","text":"Updates a user’s root values (those which are allowed to be updated)."}],"type":"topic","url":"\/documentation\/auth0\/users\/patch(_:attributes:)","role":"symbol"},"doc://com.auth0.Auth0/documentation/Auth0/Authenticator":{"title":"Authenticator","navigatorTitle":[{"text":"Authenticator","kind":"identifier"}],"kind":"symbol","type":"topic","role":"symbol","identifier":"doc:\/\/com.auth0.Auth0\/documentation\/Auth0\/Authenticator","abstract":[{"type":"text","text":"Represents an enrolled MFA authenticator for a user."}],"url":"\/documentation\/auth0\/authenticator","fragments":[{"kind":"keyword","text":"struct"},{"kind":"text","text":" "},{"text":"Authenticator","kind":"identifier"}]},"doc://com.auth0.Auth0/documentation/Auth0/webAuth(session:bundle:)":{"title":"webAuth(session:bundle:)","fragments":[{"kind":"keyword","text":"func"},{"kind":"text","text":" "},{"kind":"identifier","text":"webAuth"},{"kind":"text","text":"("},{"kind":"externalParam","text":"session"},{"kind":"text","text":": "},{"preciseIdentifier":"c:objc(cs)NSURLSession","kind":"typeIdentifier","text":"URLSession"},{"kind":"text","text":", "},{"kind":"externalParam","text":"bundle"},{"kind":"text","text":": "},{"preciseIdentifier":"c:objc(cs)NSBundle","kind":"typeIdentifier","text":"Bundle"},{"kind":"text","text":") -> "},{"preciseIdentifier":"s:5Auth07WebAuthP","kind":"typeIdentifier","text":"WebAuth"}],"url":"\/documentation\/auth0\/webauth(session:bundle:)","identifier":"doc:\/\/com.auth0.Auth0\/documentation\/Auth0\/webAuth(session:bundle:)","abstract":[{"type":"reference","identifier":"https:\/\/auth0.com\/docs\/authenticate\/login\/auth0-universal-login","isActive":true},{"type":"text","text":" client for performing web-based"},{"type":"text","text":" "},{"type":"text","text":"authentication."}],"kind":"symbol","type":"topic","role":"symbol"},"doc://com.auth0.Auth0/documentation/Auth0/AuthenticationServices":{"kind":"symbol","identifier":"doc:\/\/com.auth0.Auth0\/documentation\/Auth0\/AuthenticationServices","title":"AuthenticationServices","abstract":[],"type":"topic","url":"\/documentation\/auth0\/authenticationservices","role":"collection"},"doc://com.auth0.Auth0/documentation/Auth0/DPoPError":{"url":"\/documentation\/auth0\/dpoperror","kind":"symbol","navigatorTitle":[{"kind":"identifier","text":"DPoPError"}],"title":"DPoPError","role":"symbol","fragments":[{"kind":"keyword","text":"struct"},{"kind":"text","text":" "},{"kind":"identifier","text":"DPoPError"}],"abstract":[{"type":"text","text":"Represents an error during a DPoP operation."}],"identifier":"doc:\/\/com.auth0.Auth0\/documentation\/Auth0\/DPoPError","type":"topic"},"doc://com.auth0.Auth0/documentation/Auth0/DPoP":{"title":"DPoP","fragments":[{"text":"struct","kind":"keyword"},{"text":" ","kind":"text"},{"text":"DPoP","kind":"identifier"}],"url":"\/documentation\/auth0\/dpop","identifier":"doc:\/\/com.auth0.Auth0\/documentation\/Auth0\/DPoP","kind":"symbol","type":"topic","abstract":[{"type":"text","text":"Utilities for securing requests with DPoP (Demonstrating Proof of Possession) as described in"},{"type":"text","text":" "},{"type":"reference","isActive":true,"identifier":"https:\/\/datatracker.ietf.org\/doc\/html\/rfc9449"},{"type":"text","text":"."}],"role":"symbol","navigatorTitle":[{"text":"DPoP","kind":"identifier"}]},"https://developer.apple.com/documentation/authenticationservices/asauthorizationplatformpublickeycredentialregistration":{"url":"https:\/\/developer.apple.com\/documentation\/authenticationservices\/asauthorizationplatformpublickeycredentialregistration","type":"link","title":"ASAuthorizationPlatformPublicKeyCredentialRegistration","identifier":"https:\/\/developer.apple.com\/documentation\/authenticationservices\/asauthorizationplatformpublickeycredentialregistration","titleInlineContent":[{"type":"codeVoice","code":"ASAuthorizationPlatformPublicKeyCredentialRegistration"}]},"doc://com.auth0.Auth0/documentation/Auth0/CryptoKit":{"url":"\/documentation\/auth0\/cryptokit","identifier":"doc:\/\/com.auth0.Auth0\/documentation\/Auth0\/CryptoKit","abstract":[],"role":"collection","title":"CryptoKit","kind":"symbol","type":"topic"},"doc://com.auth0.Auth0/documentation/Auth0/users(token:session:bundle:)":{"deprecated":true,"kind":"symbol","fragments":[{"text":"func","kind":"keyword"},{"text":" ","kind":"text"},{"text":"users","kind":"identifier"},{"text":"(","kind":"text"},{"text":"token","kind":"externalParam"},{"text":": ","kind":"text"},{"preciseIdentifier":"s:SS","text":"String","kind":"typeIdentifier"},{"text":", ","kind":"text"},{"text":"session","kind":"externalParam"},{"text":": ","kind":"text"},{"preciseIdentifier":"c:objc(cs)NSURLSession","text":"URLSession","kind":"typeIdentifier"},{"text":", ","kind":"text"},{"text":"bundle","kind":"externalParam"},{"text":": ","kind":"text"},{"preciseIdentifier":"c:objc(cs)NSBundle","text":"Bundle","kind":"typeIdentifier"},{"text":") -> ","kind":"text"},{"preciseIdentifier":"s:5Auth05UsersP","text":"Users","kind":"typeIdentifier"}],"identifier":"doc:\/\/com.auth0.Auth0\/documentation\/Auth0\/users(token:session:bundle:)","title":"users(token:session:bundle:)","type":"topic","abstract":[{"type":"reference","isActive":true,"identifier":"https:\/\/auth0.com\/docs\/api\/management\/v2"},{"type":"text","text":" client for performing operations with the Users endpoints."}],"url":"\/documentation\/auth0\/users(token:session:bundle:)","role":"symbol"},"doc://com.auth0.Auth0/documentation/Auth0/Requestable":{"kind":"symbol","navigatorTitle":[{"kind":"identifier","text":"Requestable"}],"fragments":[{"text":"protocol","kind":"keyword"},{"text":" ","kind":"text"},{"text":"Requestable","kind":"identifier"}],"identifier":"doc:\/\/com.auth0.Auth0\/documentation\/Auth0\/Requestable","url":"\/documentation\/auth0\/requestable","type":"topic","abstract":[],"title":"Requestable","role":"symbol"},"doc://com.auth0.Auth0/documentation/Auth0/BiometricPolicy":{"navigatorTitle":[{"text":"BiometricPolicy","kind":"identifier"}],"role":"symbol","url":"\/documentation\/auth0\/biometricpolicy","title":"BiometricPolicy","type":"topic","fragments":[{"text":"enum","kind":"keyword"},{"text":" ","kind":"text"},{"text":"BiometricPolicy","kind":"identifier"}],"identifier":"doc:\/\/com.auth0.Auth0\/documentation\/Auth0\/BiometricPolicy","kind":"symbol","abstract":[{"type":"text","text":"Defines the policy for when a biometric prompt should be shown when using the Credentials Manager."}]},"doc://com.auth0.Auth0/documentation/Auth0/PasskeyLoginChallenge":{"navigatorTitle":[{"kind":"identifier","text":"PasskeyLoginChallenge"}],"role":"symbol","url":"\/documentation\/auth0\/passkeyloginchallenge","title":"PasskeyLoginChallenge","type":"topic","fragments":[{"kind":"keyword","text":"struct"},{"kind":"text","text":" "},{"kind":"identifier","text":"PasskeyLoginChallenge"}],"identifier":"doc:\/\/com.auth0.Auth0\/documentation\/Auth0\/PasskeyLoginChallenge","kind":"symbol","abstract":[{"type":"text","text":"A passkey login challenge."}]},"doc://com.auth0.Auth0/documentation/Auth0/AuthenticationError":{"title":"AuthenticationError","fragments":[{"text":"struct","kind":"keyword"},{"kind":"text","text":" "},{"text":"AuthenticationError","kind":"identifier"}],"url":"\/documentation\/auth0\/authenticationerror","identifier":"doc:\/\/com.auth0.Auth0\/documentation\/Auth0\/AuthenticationError","abstract":[{"type":"text","text":"Represents an error during a request to the Auth0 Authentication API."}],"kind":"symbol","type":"topic","role":"symbol","navigatorTitle":[{"text":"AuthenticationError","kind":"identifier"}]},"doc://com.auth0.Auth0/documentation/Auth0/ActorToken":{"kind":"symbol","identifier":"doc:\/\/com.auth0.Auth0\/documentation\/Auth0\/ActorToken","navigatorTitle":[{"text":"ActorToken","kind":"identifier"}],"title":"ActorToken","abstract":[{"type":"text","text":"Represents the acting party in a token exchange delegation\/impersonation flow."}],"role":"symbol","fragments":[{"text":"struct","kind":"keyword"},{"text":" ","kind":"text"},{"text":"ActorToken","kind":"identifier"}],"url":"\/documentation\/auth0\/actortoken","type":"topic"},"doc://com.auth0.Auth0/documentation/Auth0/MFAFactor":{"navigatorTitle":[{"text":"MFAFactor","kind":"identifier"}],"role":"symbol","url":"\/documentation\/auth0\/mfafactor","title":"MFAFactor","type":"topic","fragments":[{"text":"struct","kind":"keyword"},{"text":" ","kind":"text"},{"text":"MFAFactor","kind":"identifier"}],"identifier":"doc:\/\/com.auth0.Auth0\/documentation\/Auth0\/MFAFactor","kind":"symbol","abstract":[{"type":"text","text":"Represents an MFA enrollment type option."}]},"doc://com.auth0.Auth0/documentation/Auth0/AuthenticationMethods":{"navigatorTitle":[{"text":"AuthenticationMethods","kind":"identifier"}],"role":"symbol","url":"\/documentation\/auth0\/authenticationmethods","title":"AuthenticationMethods","type":"topic","fragments":[{"text":"struct","kind":"keyword"},{"text":" ","kind":"text"},{"text":"AuthenticationMethods","kind":"identifier"}],"identifier":"doc:\/\/com.auth0.Auth0\/documentation\/Auth0\/AuthenticationMethods","kind":"symbol","abstract":[{"type":"text","text":"List of authentication methods belonging to the authenticated user."}]},"doc://com.auth0.Auth0/documentation/Auth0/MfaEnrollmentError":{"kind":"symbol","title":"MfaEnrollmentError","fragments":[{"kind":"keyword","text":"struct"},{"kind":"text","text":" "},{"kind":"identifier","text":"MfaEnrollmentError"}],"url":"\/documentation\/auth0\/mfaenrollmenterror","role":"symbol","navigatorTitle":[{"kind":"identifier","text":"MfaEnrollmentError"}],"identifier":"doc:\/\/com.auth0.Auth0\/documentation\/Auth0\/MfaEnrollmentError","abstract":[{"text":"Error raised when MFA enrollment fails.","type":"text"}],"type":"topic"},"doc://com.auth0.Auth0/documentation/Auth0/Loggable":{"kind":"symbol","title":"Loggable","fragments":[{"text":"protocol","kind":"keyword"},{"text":" ","kind":"text"},{"text":"Loggable","kind":"identifier"}],"url":"\/documentation\/auth0\/loggable","role":"symbol","navigatorTitle":[{"text":"Loggable","kind":"identifier"}],"identifier":"doc:\/\/com.auth0.Auth0\/documentation\/Auth0\/Loggable","abstract":[{"type":"text","text":"A type that can log statements for debugging purposes."}],"type":"topic"},"doc://com.auth0.Auth0/documentation/Auth0/mfa(session:bundle:)":{"kind":"symbol","title":"mfa(session:bundle:)","fragments":[{"kind":"keyword","text":"func"},{"kind":"text","text":" "},{"kind":"identifier","text":"mfa"},{"kind":"text","text":"("},{"kind":"externalParam","text":"session"},{"kind":"text","text":": "},{"kind":"typeIdentifier","preciseIdentifier":"c:objc(cs)NSURLSession","text":"URLSession"},{"kind":"text","text":", "},{"kind":"externalParam","text":"bundle"},{"kind":"text","text":": "},{"kind":"typeIdentifier","preciseIdentifier":"c:objc(cs)NSBundle","text":"Bundle"},{"kind":"text","text":") -> "},{"kind":"typeIdentifier","preciseIdentifier":"s:5Auth09MFAClientP","text":"MFAClient"}],"url":"\/documentation\/auth0\/mfa(session:bundle:)","role":"symbol","identifier":"doc:\/\/com.auth0.Auth0\/documentation\/Auth0\/mfa(session:bundle:)","abstract":[{"text":"Multi-Factor Authentication (MFA) client for performing MFA operations during authentication flows.","type":"text"}],"type":"topic"},"doc://com.auth0.Auth0/documentation/Auth0/authentication(session:bundle:)":{"fragments":[{"text":"func","kind":"keyword"},{"text":" ","kind":"text"},{"text":"authentication","kind":"identifier"},{"text":"(","kind":"text"},{"text":"session","kind":"externalParam"},{"text":": ","kind":"text"},{"preciseIdentifier":"c:objc(cs)NSURLSession","text":"URLSession","kind":"typeIdentifier"},{"text":", ","kind":"text"},{"text":"bundle","kind":"externalParam"},{"text":": ","kind":"text"},{"preciseIdentifier":"c:objc(cs)NSBundle","text":"Bundle","kind":"typeIdentifier"},{"text":") -> ","kind":"text"},{"preciseIdentifier":"s:5Auth014AuthenticationP","text":"Authentication","kind":"typeIdentifier"}],"abstract":[{"identifier":"https:\/\/auth0.com\/docs\/api\/authentication","type":"reference","isActive":true},{"text":" client to authenticate a user with Database, Social,","type":"text"},{"text":" ","type":"text"},{"text":"Enterprise or Passwordless connections.","type":"text"}],"identifier":"doc:\/\/com.auth0.Auth0\/documentation\/Auth0\/authentication(session:bundle:)","type":"topic","title":"authentication(session:bundle:)","url":"\/documentation\/auth0\/authentication(session:bundle:)","kind":"symbol","role":"symbol"},"doc://com.auth0.Auth0/documentation/Auth0/MFARequirements":{"kind":"symbol","navigatorTitle":[{"text":"MFARequirements","kind":"identifier"}],"fragments":[{"text":"struct","kind":"keyword"},{"text":" ","kind":"text"},{"text":"MFARequirements","kind":"identifier"}],"identifier":"doc:\/\/com.auth0.Auth0\/documentation\/Auth0\/MFARequirements","title":"MFARequirements","abstract":[{"type":"text","text":"Represents the MFA requirements including enrollment options."}],"type":"topic","url":"\/documentation\/auth0\/mfarequirements","role":"symbol"},"doc://com.auth0.Auth0/documentation/Auth0/MyAccountAuthenticationMethods":{"title":"MyAccountAuthenticationMethods","fragments":[{"text":"protocol","kind":"keyword"},{"text":" ","kind":"text"},{"text":"MyAccountAuthenticationMethods","kind":"identifier"}],"url":"\/documentation\/auth0\/myaccountauthenticationmethods","identifier":"doc:\/\/com.auth0.Auth0\/documentation\/Auth0\/MyAccountAuthenticationMethods","kind":"symbol","type":"topic","abstract":[{"type":"text","text":"My Account API sub-client for managing the current user’s authentication methods."}],"role":"symbol","navigatorTitle":[{"text":"MyAccountAuthenticationMethods","kind":"identifier"}]},"doc://com.auth0.Auth0/documentation/Auth0/PushEnrollmentChallenge":{"kind":"symbol","navigatorTitle":[{"text":"PushEnrollmentChallenge","kind":"identifier"}],"fragments":[{"text":"struct","kind":"keyword"},{"text":" ","kind":"text"},{"text":"PushEnrollmentChallenge","kind":"identifier"}],"identifier":"doc:\/\/com.auth0.Auth0\/documentation\/Auth0\/PushEnrollmentChallenge","title":"PushEnrollmentChallenge","type":"topic","abstract":[{"text":"A Push enrollment challenge.","type":"text"}],"url":"\/documentation\/auth0\/pushenrollmentchallenge","role":"symbol"},"doc://com.auth0.Auth0/documentation/Auth0/UserAgents":{"kind":"article","identifier":"doc:\/\/com.auth0.Auth0\/documentation\/Auth0\/UserAgents","url":"\/documentation\/auth0\/useragents","type":"topic","title":"ASWebAuthenticationSession vs SFSafariViewController (iOS)","abstract":[],"role":"article"},"doc://com.auth0.Auth0/documentation/Auth0/AuthenticationResult":{"title":"AuthenticationResult","fragments":[{"kind":"keyword","text":"typealias"},{"kind":"text","text":" "},{"kind":"identifier","text":"AuthenticationResult"}],"url":"\/documentation\/auth0\/authenticationresult","identifier":"doc:\/\/com.auth0.Auth0\/documentation\/Auth0\/AuthenticationResult","abstract":[{"code":"Result","type":"codeVoice"},{"text":" wrapper for Authentication API operations.","type":"text"}],"kind":"symbol","type":"topic","role":"symbol","navigatorTitle":[{"kind":"identifier","text":"AuthenticationResult"}]},"https://datatracker.ietf.org/doc/html/rfc9449":{"title":"RFC 9449","titleInlineContent":[{"type":"text","text":"RFC 9449"}],"type":"link","url":"https:\/\/datatracker.ietf.org\/doc\/html\/rfc9449","identifier":"https:\/\/datatracker.ietf.org\/doc\/html\/rfc9449"},"doc://com.auth0.Auth0/documentation/Auth0/UserInfo":{"title":"UserInfo","navigatorTitle":[{"text":"UserInfo","kind":"identifier"}],"kind":"symbol","type":"topic","role":"symbol","identifier":"doc:\/\/com.auth0.Auth0\/documentation\/Auth0\/UserInfo","abstract":[{"type":"text","text":"OIDC Standard Claims user information."}],"url":"\/documentation\/auth0\/userinfo","fragments":[{"kind":"keyword","text":"struct"},{"kind":"text","text":" "},{"kind":"identifier","text":"UserInfo"}]},"doc://com.auth0.Auth0/documentation/Auth0/webAuth(clientId:domain:session:)":{"fragments":[{"text":"func","kind":"keyword"},{"text":" ","kind":"text"},{"text":"webAuth","kind":"identifier"},{"text":"(","kind":"text"},{"text":"clientId","kind":"externalParam"},{"text":": ","kind":"text"},{"text":"String","kind":"typeIdentifier","preciseIdentifier":"s:SS"},{"text":", ","kind":"text"},{"text":"domain","kind":"externalParam"},{"text":": ","kind":"text"},{"text":"String","kind":"typeIdentifier","preciseIdentifier":"s:SS"},{"text":", ","kind":"text"},{"text":"session","kind":"externalParam"},{"text":": ","kind":"text"},{"text":"URLSession","kind":"typeIdentifier","preciseIdentifier":"c:objc(cs)NSURLSession"},{"text":") -> ","kind":"text"},{"text":"WebAuth","kind":"typeIdentifier","preciseIdentifier":"s:5Auth07WebAuthP"}],"abstract":[{"type":"reference","isActive":true,"identifier":"https:\/\/auth0.com\/docs\/authenticate\/login\/auth0-universal-login"},{"type":"text","text":" client for performing web-based"},{"type":"text","text":" "},{"type":"text","text":"authentication."}],"type":"topic","title":"webAuth(clientId:domain:session:)","url":"\/documentation\/auth0\/webauth(clientid:domain:session:)","identifier":"doc:\/\/com.auth0.Auth0\/documentation\/Auth0\/webAuth(clientId:domain:session:)","kind":"symbol","role":"symbol"},"doc://com.auth0.Auth0/documentation/Auth0/MFARequiredErrorPayload":{"title":"MFARequiredErrorPayload","fragments":[{"text":"struct","kind":"keyword"},{"text":" ","kind":"text"},{"text":"MFARequiredErrorPayload","kind":"identifier"}],"url":"\/documentation\/auth0\/mfarequirederrorpayload","identifier":"doc:\/\/com.auth0.Auth0\/documentation\/Auth0\/MFARequiredErrorPayload","abstract":[{"type":"text","text":"Represents the payload returned when multifactor authentication is required."}],"kind":"symbol","type":"topic","role":"symbol","navigatorTitle":[{"text":"MFARequiredErrorPayload","kind":"identifier"}]},"doc://com.auth0.Auth0/documentation/Auth0/authentication(clientId:domain:session:)":{"fragments":[{"text":"func","kind":"keyword"},{"text":" ","kind":"text"},{"text":"authentication","kind":"identifier"},{"text":"(","kind":"text"},{"text":"clientId","kind":"externalParam"},{"text":": ","kind":"text"},{"text":"String","preciseIdentifier":"s:SS","kind":"typeIdentifier"},{"text":", ","kind":"text"},{"text":"domain","kind":"externalParam"},{"text":": ","kind":"text"},{"text":"String","preciseIdentifier":"s:SS","kind":"typeIdentifier"},{"text":", ","kind":"text"},{"text":"session","kind":"externalParam"},{"text":": ","kind":"text"},{"text":"URLSession","preciseIdentifier":"c:objc(cs)NSURLSession","kind":"typeIdentifier"},{"text":") -> ","kind":"text"},{"text":"Authentication","preciseIdentifier":"s:5Auth014AuthenticationP","kind":"typeIdentifier"}],"abstract":[{"identifier":"https:\/\/auth0.com\/docs\/api\/authentication","isActive":true,"type":"reference"},{"text":" client to authenticate a user with Database, Social,","type":"text"},{"text":" ","type":"text"},{"text":"Enterprise or Passwordless connections.","type":"text"}],"identifier":"doc:\/\/com.auth0.Auth0\/documentation\/Auth0\/authentication(clientId:domain:session:)","title":"authentication(clientId:domain:session:)","url":"\/documentation\/auth0\/authentication(clientid:domain:session:)","type":"topic","kind":"symbol","role":"symbol"},"doc://com.auth0.Auth0/documentation/Auth0/WebAuthError":{"url":"\/documentation\/auth0\/webautherror","navigatorTitle":[{"text":"WebAuthError","kind":"identifier"}],"identifier":"doc:\/\/com.auth0.Auth0\/documentation\/Auth0\/WebAuthError","fragments":[{"text":"struct","kind":"keyword"},{"text":" ","kind":"text"},{"text":"WebAuthError","kind":"identifier"}],"abstract":[{"text":"Represents an error during a Web Auth operation.","type":"text"}],"role":"symbol","title":"WebAuthError","kind":"symbol","type":"topic"},"doc://com.auth0.Auth0/documentation/Auth0/myAccount(token:domain:session:)":{"title":"myAccount(token:domain:session:)","fragments":[{"text":"func","kind":"keyword"},{"text":" ","kind":"text"},{"text":"myAccount","kind":"identifier"},{"text":"(","kind":"text"},{"text":"token","kind":"externalParam"},{"text":": ","kind":"text"},{"preciseIdentifier":"s:SS","text":"String","kind":"typeIdentifier"},{"text":", ","kind":"text"},{"text":"domain","kind":"externalParam"},{"text":": ","kind":"text"},{"preciseIdentifier":"s:SS","text":"String","kind":"typeIdentifier"},{"text":", ","kind":"text"},{"text":"session","kind":"externalParam"},{"text":": ","kind":"text"},{"preciseIdentifier":"c:objc(cs)NSURLSession","text":"URLSession","kind":"typeIdentifier"},{"text":") -> ","kind":"text"},{"preciseIdentifier":"s:5Auth09MyAccountP","text":"MyAccount","kind":"typeIdentifier"}],"url":"\/documentation\/auth0\/myaccount(token:domain:session:)","identifier":"doc:\/\/com.auth0.Auth0\/documentation\/Auth0\/myAccount(token:domain:session:)","abstract":[{"type":"text","text":"Auth0 My Account API client for managing the current user’s account."}],"kind":"symbol","type":"topic","role":"symbol"},"https://auth0.com/docs/api/authentication#multi-factor-authentication":{"title":"Auth0 Multifactor Authentication API","titleInlineContent":[{"text":"Auth0 Multifactor Authentication API","type":"text"}],"type":"link","url":"https:\/\/auth0.com\/docs\/api\/authentication#multi-factor-authentication","identifier":"https:\/\/auth0.com\/docs\/api\/authentication#multi-factor-authentication"},"doc://com.auth0.Auth0/documentation/Auth0/PasskeySignupChallenge":{"url":"\/documentation\/auth0\/passkeysignupchallenge","kind":"symbol","navigatorTitle":[{"text":"PasskeySignupChallenge","kind":"identifier"}],"title":"PasskeySignupChallenge","role":"symbol","fragments":[{"text":"struct","kind":"keyword"},{"text":" ","kind":"text"},{"text":"PasskeySignupChallenge","kind":"identifier"}],"abstract":[{"text":"A passkey signup challenge.","type":"text"}],"identifier":"doc:\/\/com.auth0.Auth0\/documentation\/Auth0\/PasskeySignupChallenge","type":"topic"},"doc://com.auth0.Auth0/documentation/Auth0/LoginPasskey":{"title":"LoginPasskey","fragments":[{"kind":"keyword","text":"protocol"},{"kind":"text","text":" "},{"kind":"identifier","text":"LoginPasskey"}],"url":"\/documentation\/auth0\/loginpasskey","identifier":"doc:\/\/com.auth0.Auth0\/documentation\/Auth0\/LoginPasskey","kind":"symbol","type":"topic","abstract":[{"type":"text","text":"The login passkey credential obtained from the "},{"isActive":true,"identifier":"https:\/\/developer.apple.com\/documentation\/authenticationservices\/asauthorizationcontrollerdelegate","type":"reference"},{"type":"text","text":" delegate."},{"type":"text","text":" "},{"type":"text","text":"Contains the subset of relevant properties from "},{"isActive":true,"identifier":"https:\/\/developer.apple.com\/documentation\/authenticationservices\/asauthorizationplatformpublickeycredentialassertion","type":"reference"},{"type":"text","text":"."}],"role":"symbol","navigatorTitle":[{"kind":"identifier","text":"LoginPasskey"}]},"doc://com.auth0.Auth0/documentation/Auth0/JWK":{"kind":"symbol","title":"JWK","fragments":[{"text":"struct","kind":"keyword"},{"text":" ","kind":"text"},{"text":"JWK","kind":"identifier"}],"url":"\/documentation\/auth0\/jwk","role":"symbol","navigatorTitle":[{"text":"JWK","kind":"identifier"}],"identifier":"doc:\/\/com.auth0.Auth0\/documentation\/Auth0\/JWK","abstract":[{"type":"text","text":"Cryptographic public key of your Auth0 tenant."}],"type":"topic"},"doc://com.auth0.Auth0/documentation/Auth0/MFAChallenge":{"kind":"symbol","navigatorTitle":[{"kind":"identifier","text":"MFAChallenge"}],"fragments":[{"kind":"keyword","text":"struct"},{"kind":"text","text":" "},{"kind":"identifier","text":"MFAChallenge"}],"identifier":"doc:\/\/com.auth0.Auth0\/documentation\/Auth0\/MFAChallenge","url":"\/documentation\/auth0\/mfachallenge","type":"topic","abstract":[{"text":"Represents an MFA challenge issued to the user during the authentication flow.","type":"text"}],"title":"MFAChallenge","role":"symbol"},"https://auth0.com/docs/api/authentication":{"identifier":"https:\/\/auth0.com\/docs\/api\/authentication","type":"link","title":"Auth0 Authentication API","titleInlineContent":[{"type":"text","text":"Auth0 Authentication API"}],"url":"https:\/\/auth0.com\/docs\/api\/authentication"},"doc://com.auth0.Auth0/documentation/Auth0/WebAuth":{"kind":"symbol","navigatorTitle":[{"text":"WebAuth","kind":"identifier"}],"fragments":[{"kind":"keyword","text":"protocol"},{"kind":"text","text":" "},{"kind":"identifier","text":"WebAuth"}],"identifier":"doc:\/\/com.auth0.Auth0\/documentation\/Auth0\/WebAuth","title":"WebAuth","url":"\/documentation\/auth0\/webauth","abstract":[{"type":"text","text":"Web-based authentication using Auth0."}],"type":"topic","role":"symbol"},"doc://com.auth0.Auth0/documentation/Auth0/Logger":{"kind":"symbol","title":"Logger","fragments":[{"kind":"keyword","text":"protocol"},{"kind":"text","text":" "},{"kind":"identifier","text":"Logger"}],"url":"\/documentation\/auth0\/logger","role":"symbol","navigatorTitle":[{"kind":"identifier","text":"Logger"}],"identifier":"doc:\/\/com.auth0.Auth0\/documentation\/Auth0\/Logger","abstract":[{"type":"text","text":"Logger for debugging purposes."}],"type":"topic"},"doc://com.auth0.Auth0/documentation/Auth0/users(token:domain:session:)":{"fragments":[{"text":"func","kind":"keyword"},{"text":" ","kind":"text"},{"text":"users","kind":"identifier"},{"text":"(","kind":"text"},{"text":"token","kind":"externalParam"},{"text":": ","kind":"text"},{"preciseIdentifier":"s:SS","text":"String","kind":"typeIdentifier"},{"text":", ","kind":"text"},{"text":"domain","kind":"externalParam"},{"text":": ","kind":"text"},{"preciseIdentifier":"s:SS","text":"String","kind":"typeIdentifier"},{"text":", ","kind":"text"},{"text":"session","kind":"externalParam"},{"text":": ","kind":"text"},{"preciseIdentifier":"c:objc(cs)NSURLSession","text":"URLSession","kind":"typeIdentifier"},{"text":") -> ","kind":"text"},{"preciseIdentifier":"s:5Auth05UsersP","text":"Users","kind":"typeIdentifier"}],"deprecated":true,"abstract":[{"isActive":true,"type":"reference","identifier":"https:\/\/auth0.com\/docs\/api\/management\/v2"},{"type":"text","text":" client for performing operations with the Users endpoints."}],"identifier":"doc:\/\/com.auth0.Auth0\/documentation\/Auth0\/users(token:domain:session:)","type":"topic","title":"users(token:domain:session:)","url":"\/documentation\/auth0\/users(token:domain:session:)","kind":"symbol","role":"symbol"},"doc://com.auth0.Auth0/documentation/Auth0/SenderConstraining":{"title":"SenderConstraining","fragments":[{"kind":"keyword","text":"protocol"},{"kind":"text","text":" "},{"kind":"identifier","text":"SenderConstraining"}],"url":"\/documentation\/auth0\/senderconstraining","identifier":"doc:\/\/com.auth0.Auth0\/documentation\/Auth0\/SenderConstraining","abstract":[{"text":"A type that can use DPoP for securing requests.","type":"text"}],"kind":"symbol","type":"topic","role":"symbol","navigatorTitle":[{"text":"SenderConstraining","kind":"identifier"}]},"doc://com.auth0.Auth0/documentation/Auth0/Request":{"fragments":[{"text":"struct","kind":"keyword"},{"text":" ","kind":"text"},{"text":"Request","kind":"identifier"}],"abstract":[{"type":"text","text":"Auth0 API request."}],"identifier":"doc:\/\/com.auth0.Auth0\/documentation\/Auth0\/Request","type":"topic","title":"Request","url":"\/documentation\/auth0\/request","kind":"symbol","role":"symbol","navigatorTitle":[{"text":"Request","kind":"identifier"}]},"doc://com.auth0.Auth0/documentation/Auth0/PasswordlessType":{"fragments":[{"text":"enum","kind":"keyword"},{"text":" ","kind":"text"},{"text":"PasswordlessType","kind":"identifier"}],"abstract":[{"type":"text","text":"Types of passwordless authentication."}],"type":"topic","identifier":"doc:\/\/com.auth0.Auth0\/documentation\/Auth0\/PasswordlessType","url":"\/documentation\/auth0\/passwordlesstype","title":"PasswordlessType","kind":"symbol","role":"symbol","navigatorTitle":[{"text":"PasswordlessType","kind":"identifier"}]},"doc://com.auth0.Auth0/documentation/Auth0/ActClaim":{"type":"topic","fragments":[{"kind":"keyword","text":"class"},{"text":" ","kind":"text"},{"text":"ActClaim","kind":"identifier"}],"url":"\/documentation\/auth0\/actclaim","abstract":[{"type":"text","text":"Represents the "},{"code":"act","type":"codeVoice"},{"type":"text","text":" (actor) claim from an ID token issued during a token exchange delegation flow."}],"role":"symbol","kind":"symbol","identifier":"doc:\/\/com.auth0.Auth0\/documentation\/Auth0\/ActClaim","navigatorTitle":[{"kind":"identifier","text":"ActClaim"}],"title":"ActClaim"},"doc://com.auth0.Auth0/documentation/Auth0/RefreshTokens":{"kind":"article","identifier":"doc:\/\/com.auth0.Auth0\/documentation\/Auth0\/RefreshTokens","url":"\/documentation\/auth0\/refreshtokens","type":"topic","abstract":[],"title":"Refresh Tokens: Common Errors","role":"article"},"doc://com.auth0.Auth0/documentation/Auth0/Auth0APIError":{"fragments":[{"text":"protocol","kind":"keyword"},{"text":" ","kind":"text"},{"text":"Auth0APIError","kind":"identifier"}],"abstract":[{"type":"text","text":"Generic representation of Auth0 API errors."}],"identifier":"doc:\/\/com.auth0.Auth0\/documentation\/Auth0\/Auth0APIError","title":"Auth0APIError","url":"\/documentation\/auth0\/auth0apierror","type":"topic","kind":"symbol","role":"symbol","navigatorTitle":[{"kind":"identifier","text":"Auth0APIError"}]},"doc://com.auth0.Auth0/documentation/Auth0/MFAVerifyError":{"navigatorTitle":[{"kind":"identifier","text":"MFAVerifyError"}],"role":"symbol","url":"\/documentation\/auth0\/mfaverifyerror","title":"MFAVerifyError","type":"topic","fragments":[{"kind":"keyword","text":"struct"},{"kind":"text","text":" "},{"kind":"identifier","text":"MFAVerifyError"}],"identifier":"doc:\/\/com.auth0.Auth0\/documentation\/Auth0\/MFAVerifyError","kind":"symbol","abstract":[{"type":"text","text":"Error raised when MFA verification fails."}]},"doc://com.auth0.Auth0/documentation/Auth0/CredentialsStorage":{"url":"\/documentation\/auth0\/credentialsstorage","kind":"symbol","navigatorTitle":[{"text":"CredentialsStorage","kind":"identifier"}],"title":"CredentialsStorage","role":"symbol","fragments":[{"text":"protocol","kind":"keyword"},{"text":" ","kind":"text"},{"text":"CredentialsStorage","kind":"identifier"}],"abstract":[{"type":"text","text":"Generic storage API for storing credentials."}],"type":"topic","identifier":"doc:\/\/com.auth0.Auth0\/documentation\/Auth0\/CredentialsStorage"},"doc://com.auth0.Auth0/documentation/Auth0/Authentication":{"title":"Authentication","navigatorTitle":[{"text":"Authentication","kind":"identifier"}],"kind":"symbol","type":"topic","role":"symbol","identifier":"doc:\/\/com.auth0.Auth0\/documentation\/Auth0\/Authentication","abstract":[{"type":"text","text":"Client for the "},{"type":"reference","identifier":"https:\/\/auth0.com\/docs\/api\/authentication","isActive":true},{"type":"text","text":"."}],"url":"\/documentation\/auth0\/authentication","fragments":[{"kind":"keyword","text":"protocol"},{"text":" ","kind":"text"},{"kind":"identifier","text":"Authentication"}]},"doc://com.auth0.Auth0/documentation/Auth0/PhoneEnrollmentChallenge":{"navigatorTitle":[{"text":"PhoneEnrollmentChallenge","kind":"identifier"}],"role":"symbol","url":"\/documentation\/auth0\/phoneenrollmentchallenge","title":"PhoneEnrollmentChallenge","type":"topic","fragments":[{"text":"struct","kind":"keyword"},{"text":" ","kind":"text"},{"kind":"identifier","text":"PhoneEnrollmentChallenge"}],"identifier":"doc:\/\/com.auth0.Auth0\/documentation\/Auth0\/PhoneEnrollmentChallenge","kind":"symbol","abstract":[{"type":"text","text":"A Phone enrollment challenge."}]},"doc://com.auth0.Auth0/documentation/Auth0/PasskeyEnrollmentChallenge":{"navigatorTitle":[{"kind":"identifier","text":"PasskeyEnrollmentChallenge"}],"role":"symbol","url":"\/documentation\/auth0\/passkeyenrollmentchallenge","title":"PasskeyEnrollmentChallenge","type":"topic","fragments":[{"kind":"keyword","text":"struct"},{"kind":"text","text":" "},{"kind":"identifier","text":"PasskeyEnrollmentChallenge"}],"identifier":"doc:\/\/com.auth0.Auth0\/documentation\/Auth0\/PasskeyEnrollmentChallenge","kind":"symbol","abstract":[{"text":"A passkey enrollment challenge.","type":"text"}]},"doc://com.auth0.Auth0/documentation/Auth0/PasskeyDeviceType":{"url":"\/documentation\/auth0\/passkeydevicetype","navigatorTitle":[{"text":"PasskeyDeviceType","kind":"identifier"}],"identifier":"doc:\/\/com.auth0.Auth0\/documentation\/Auth0\/PasskeyDeviceType","fragments":[{"text":"enum","kind":"keyword"},{"text":" ","kind":"text"},{"text":"PasskeyDeviceType","kind":"identifier"}],"abstract":[{"text":"Kind of device the passkey is stored on as defined by backup eligibility.","type":"text"}],"role":"symbol","title":"PasskeyDeviceType","kind":"symbol","type":"topic"},"doc://com.auth0.Auth0/documentation/Auth0/JWKS":{"kind":"symbol","navigatorTitle":[{"text":"JWKS","kind":"identifier"}],"fragments":[{"text":"struct","kind":"keyword"},{"text":" ","kind":"text"},{"text":"JWKS","kind":"identifier"}],"identifier":"doc:\/\/com.auth0.Auth0\/documentation\/Auth0\/JWKS","title":"JWKS","type":"topic","abstract":[{"type":"text","text":"The JSON Web Key Set (JWKS) of your Auth0 tenant."}],"url":"\/documentation\/auth0\/jwks","role":"symbol"},"doc://com.auth0.Auth0/documentation/Auth0/WebAuthUserAgent":{"url":"\/documentation\/auth0\/webauthuseragent","kind":"symbol","navigatorTitle":[{"kind":"identifier","text":"WebAuthUserAgent"}],"title":"WebAuthUserAgent","role":"symbol","fragments":[{"kind":"keyword","text":"protocol"},{"kind":"text","text":" "},{"kind":"identifier","text":"WebAuthUserAgent"}],"abstract":[{"type":"text","text":"The external user agent used to perform a web-based operation."}],"type":"topic","identifier":"doc:\/\/com.auth0.Auth0\/documentation\/Auth0\/WebAuthUserAgent"},"doc://com.auth0.Auth0/documentation/Auth0/PreferredAuthenticationMethod":{"title":"PreferredAuthenticationMethod","fragments":[{"kind":"keyword","text":"enum"},{"kind":"text","text":" "},{"kind":"identifier","text":"PreferredAuthenticationMethod"}],"url":"\/documentation\/auth0\/preferredauthenticationmethod","identifier":"doc:\/\/com.auth0.Auth0\/documentation\/Auth0\/PreferredAuthenticationMethod","abstract":[],"kind":"symbol","type":"topic","role":"symbol","navigatorTitle":[{"kind":"identifier","text":"PreferredAuthenticationMethod"}]},"doc://com.auth0.Auth0/documentation/Auth0/MyAccount":{"url":"\/documentation\/auth0\/myaccount","kind":"symbol","navigatorTitle":[{"text":"MyAccount","kind":"identifier"}],"title":"MyAccount","role":"symbol","fragments":[{"text":"protocol","kind":"keyword"},{"text":" ","kind":"text"},{"text":"MyAccount","kind":"identifier"}],"abstract":[{"text":"My Account API client for managing the current user’s account.","type":"text"}],"identifier":"doc:\/\/com.auth0.Auth0\/documentation\/Auth0\/MyAccount","type":"topic"},"doc://com.auth0.Auth0/documentation/Auth0/Telemetry":{"kind":"symbol","navigatorTitle":[{"text":"Telemetry","kind":"identifier"}],"fragments":[{"text":"struct","kind":"keyword"},{"text":" ","kind":"text"},{"text":"Telemetry","kind":"identifier"}],"identifier":"doc:\/\/com.auth0.Auth0\/documentation\/Auth0\/Telemetry","title":"Telemetry","type":"topic","url":"\/documentation\/auth0\/telemetry","abstract":[{"text":"Generates and sets the ","type":"text"},{"code":"Auth0-Client","type":"codeVoice"},{"text":" header.","type":"text"}],"role":"symbol"},"doc://com.auth0.Auth0/documentation/Auth0/MfaListAuthenticatorsError":{"kind":"symbol","navigatorTitle":[{"text":"MfaListAuthenticatorsError","kind":"identifier"}],"fragments":[{"text":"struct","kind":"keyword"},{"text":" ","kind":"text"},{"text":"MfaListAuthenticatorsError","kind":"identifier"}],"identifier":"doc:\/\/com.auth0.Auth0\/documentation\/Auth0\/MfaListAuthenticatorsError","title":"MfaListAuthenticatorsError","url":"\/documentation\/auth0\/mfalistauthenticatorserror","abstract":[{"text":"Error raised when listing MFA authenticators fails.","type":"text"}],"type":"topic","role":"symbol"},"doc://com.auth0.Auth0/documentation/Auth0/MFAClient":{"url":"\/documentation\/auth0\/mfaclient","kind":"symbol","navigatorTitle":[{"kind":"identifier","text":"MFAClient"}],"title":"MFAClient","role":"symbol","fragments":[{"kind":"keyword","text":"protocol"},{"kind":"text","text":" "},{"kind":"identifier","text":"MFAClient"}],"abstract":[{"type":"text","text":"Client for the "},{"type":"reference","isActive":true,"identifier":"https:\/\/auth0.com\/docs\/api\/authentication#multi-factor-authentication"},{"type":"text","text":"."}],"type":"topic","identifier":"doc:\/\/com.auth0.Auth0\/documentation\/Auth0\/MFAClient"},"doc://com.auth0.Auth0/documentation/Auth0/myAccount(token:session:bundle:)":{"title":"myAccount(token:session:bundle:)","fragments":[{"text":"func","kind":"keyword"},{"text":" ","kind":"text"},{"text":"myAccount","kind":"identifier"},{"text":"(","kind":"text"},{"text":"token","kind":"externalParam"},{"text":": ","kind":"text"},{"preciseIdentifier":"s:SS","text":"String","kind":"typeIdentifier"},{"text":", ","kind":"text"},{"text":"session","kind":"externalParam"},{"text":": ","kind":"text"},{"preciseIdentifier":"c:objc(cs)NSURLSession","text":"URLSession","kind":"typeIdentifier"},{"text":", ","kind":"text"},{"text":"bundle","kind":"externalParam"},{"text":": ","kind":"text"},{"preciseIdentifier":"c:objc(cs)NSBundle","text":"Bundle","kind":"typeIdentifier"},{"text":") -> ","kind":"text"},{"preciseIdentifier":"s:5Auth09MyAccountP","text":"MyAccount","kind":"typeIdentifier"}],"url":"\/documentation\/auth0\/myaccount(token:session:bundle:)","identifier":"doc:\/\/com.auth0.Auth0\/documentation\/Auth0\/myAccount(token:session:bundle:)","abstract":[{"type":"text","text":"Auth0 My Account API client for managing the current user’s account."}],"type":"topic","kind":"symbol","role":"symbol"},"doc://com.auth0.Auth0/documentation/Auth0/DatabaseUser":{"kind":"symbol","navigatorTitle":[{"text":"DatabaseUser","kind":"identifier"}],"fragments":[{"text":"typealias","kind":"keyword"},{"text":" ","kind":"text"},{"text":"DatabaseUser","kind":"identifier"}],"identifier":"doc:\/\/com.auth0.Auth0\/documentation\/Auth0\/DatabaseUser","title":"DatabaseUser","abstract":[{"type":"text","text":"A newly created database user (just the email, username, and email verified flag)."}],"type":"topic","url":"\/documentation\/auth0\/databaseuser","role":"symbol"},"doc://com.auth0.Auth0/documentation/Auth0/authorizeWithRequestUri(bundle:)":{"title":"authorizeWithRequestUri(bundle:)","fragments":[{"kind":"keyword","text":"func"},{"kind":"text","text":" "},{"kind":"identifier","text":"authorizeWithRequestUri"},{"kind":"text","text":"("},{"kind":"externalParam","text":"bundle"},{"kind":"text","text":": "},{"kind":"typeIdentifier","preciseIdentifier":"c:objc(cs)NSBundle","text":"Bundle"},{"kind":"text","text":") -> "},{"kind":"typeIdentifier","preciseIdentifier":"s:5Auth07PARAuthP","text":"PARAuth"}],"url":"\/documentation\/auth0\/authorizewithrequesturi(bundle:)","identifier":"doc:\/\/com.auth0.Auth0\/documentation\/Auth0\/authorizeWithRequestUri(bundle:)","abstract":[{"text":"PAR (Pushed Authorization Request) client for performing the browser authorization step of a PAR flow.","type":"text"}],"type":"topic","kind":"symbol","role":"symbol"},"doc://com.auth0.Auth0/documentation/Auth0/Swift":{"title":"Swift","url":"\/documentation\/auth0\/swift","identifier":"doc:\/\/com.auth0.Auth0\/documentation\/Auth0\/Swift","abstract":[],"kind":"symbol","type":"topic","role":"collection"},"doc://com.auth0.Auth0/documentation/Auth0/Trackable":{"kind":"symbol","title":"Trackable","fragments":[{"text":"protocol","kind":"keyword"},{"text":" ","kind":"text"},{"text":"Trackable","kind":"identifier"}],"url":"\/documentation\/auth0\/trackable","role":"symbol","navigatorTitle":[{"text":"Trackable","kind":"identifier"}],"identifier":"doc:\/\/com.auth0.Auth0\/documentation\/Auth0\/Trackable","abstract":[{"text":"A type that can send the ","type":"text"},{"code":"Auth0-Client","type":"codeVoice"},{"text":" header on every request to Auth0.","type":"text"}],"type":"topic"},"doc://com.auth0.Auth0/documentation/Auth0/Factor":{"title":"Factor","fragments":[{"kind":"keyword","text":"struct"},{"kind":"text","text":" "},{"kind":"identifier","text":"Factor"}],"url":"\/documentation\/auth0\/factor","identifier":"doc:\/\/com.auth0.Auth0\/documentation\/Auth0\/Factor","abstract":[],"type":"topic","kind":"symbol","role":"symbol","navigatorTitle":[{"kind":"identifier","text":"Factor"}]},"doc://com.auth0.Auth0/documentation/Auth0/Auth0Error":{"navigatorTitle":[{"kind":"identifier","text":"Auth0Error"}],"role":"symbol","url":"\/documentation\/auth0\/auth0error","title":"Auth0Error","type":"topic","fragments":[{"kind":"keyword","text":"protocol"},{"kind":"text","text":" "},{"kind":"identifier","text":"Auth0Error"}],"identifier":"doc:\/\/com.auth0.Auth0\/documentation\/Auth0\/Auth0Error","kind":"symbol","abstract":[{"text":"Generic representation of Auth0 errors.","type":"text"}]},"doc://com.auth0.Auth0/documentation/Auth0/UserPatchAttributes":{"title":"UserPatchAttributes","fragments":[{"kind":"keyword","text":"class"},{"kind":"text","text":" "},{"kind":"identifier","text":"UserPatchAttributes"}],"url":"\/documentation\/auth0\/userpatchattributes","identifier":"doc:\/\/com.auth0.Auth0\/documentation\/Auth0\/UserPatchAttributes","abstract":[{"type":"text","text":"User attributes that can be updated using the "},{"type":"reference","identifier":"doc:\/\/com.auth0.Auth0\/documentation\/Auth0\/Users\/patch(_:attributes:)","isActive":true},{"type":"text","text":" method of "},{"type":"reference","identifier":"doc:\/\/com.auth0.Auth0\/documentation\/Auth0\/Users","isActive":true},{"type":"text","text":"."}],"kind":"symbol","type":"topic","role":"symbol","deprecated":true,"navigatorTitle":[{"kind":"identifier","text":"UserPatchAttributes"}]},"doc://com.auth0.Auth0/documentation/Auth0/Challenge":{"title":"Challenge","fragments":[{"kind":"keyword","text":"struct"},{"kind":"text","text":" "},{"kind":"identifier","text":"Challenge"}],"url":"\/documentation\/auth0\/challenge","identifier":"doc:\/\/com.auth0.Auth0\/documentation\/Auth0\/Challenge","kind":"symbol","type":"topic","abstract":[{"text":"A multi-factor challenge.","type":"text"}],"role":"symbol","navigatorTitle":[{"kind":"identifier","text":"Challenge"}]},"doc://com.auth0.Auth0/documentation/Auth0/Users":{"type":"topic","fragments":[{"kind":"keyword","text":"protocol"},{"text":" ","kind":"text"},{"text":"Users","kind":"identifier"}],"url":"\/documentation\/auth0\/users","abstract":[{"type":"text","text":"Client for the Users endpoints of the Auth0 "},{"identifier":"https:\/\/auth0.com\/docs\/api\/management\/v2","isActive":true,"type":"reference"},{"text":".","type":"text"}],"role":"symbol","deprecated":true,"kind":"symbol","identifier":"doc:\/\/com.auth0.Auth0\/documentation\/Auth0\/Users","navigatorTitle":[{"kind":"identifier","text":"Users"}],"title":"Users"},"doc://com.auth0.Auth0/documentation/Auth0/RecoveryCodeEnrollmentChallenge":{"navigatorTitle":[{"text":"RecoveryCodeEnrollmentChallenge","kind":"identifier"}],"role":"symbol","url":"\/documentation\/auth0\/recoverycodeenrollmentchallenge","title":"RecoveryCodeEnrollmentChallenge","type":"topic","fragments":[{"text":"struct","kind":"keyword"},{"text":" ","kind":"text"},{"text":"RecoveryCodeEnrollmentChallenge","kind":"identifier"}],"identifier":"doc:\/\/com.auth0.Auth0\/documentation\/Auth0\/RecoveryCodeEnrollmentChallenge","kind":"symbol","abstract":[{"type":"text","text":"A Recovery code enrollment challenge."}]},"doc://com.auth0.Auth0/documentation/Auth0/WebAuthProvider":{"url":"\/documentation\/auth0\/webauthprovider","kind":"symbol","navigatorTitle":[{"text":"WebAuthProvider","kind":"identifier"}],"title":"WebAuthProvider","role":"symbol","fragments":[{"text":"typealias","kind":"keyword"},{"text":" ","kind":"text"},{"text":"WebAuthProvider","kind":"identifier"}],"abstract":[{"type":"text","text":"Thunk that returns a function that creates and returns a "},{"type":"reference","identifier":"doc:\/\/com.auth0.Auth0\/documentation\/Auth0\/WebAuthUserAgent","isActive":true},{"type":"text","text":" to perform a web-based operation."},{"type":"text","text":" "},{"type":"text","text":"The "},{"type":"reference","identifier":"doc:\/\/com.auth0.Auth0\/documentation\/Auth0\/WebAuthUserAgent","isActive":true},{"type":"text","text":" opens the URL in an external user agent and then invokes the callback when done."}],"type":"topic","identifier":"doc:\/\/com.auth0.Auth0\/documentation\/Auth0\/WebAuthProvider"},"https://developer.apple.com/documentation/authenticationservices/asauthorizationplatformpublickeycredentialassertion":{"identifier":"https:\/\/developer.apple.com\/documentation\/authenticationservices\/asauthorizationplatformpublickeycredentialassertion","titleInlineContent":[{"code":"ASAuthorizationPlatformPublicKeyCredentialAssertion","type":"codeVoice"}],"type":"link","title":"ASAuthorizationPlatformPublicKeyCredentialAssertion","url":"https:\/\/developer.apple.com\/documentation\/authenticationservices\/asauthorizationplatformpublickeycredentialassertion"},"doc://com.auth0.Auth0/documentation/Auth0/MyAccountClient":{"url":"\/documentation\/auth0\/myaccountclient","kind":"symbol","navigatorTitle":[{"text":"MyAccountClient","kind":"identifier"}],"title":"MyAccountClient","role":"symbol","fragments":[{"text":"protocol","kind":"keyword"},{"text":" ","kind":"text"},{"text":"MyAccountClient","kind":"identifier"}],"abstract":[{"text":"A client for the My Account API.","type":"text"},{"text":" ","type":"text"},{"text":"Adopting types could be either the root client or a leaf sub-client.","type":"text"}],"type":"topic","identifier":"doc:\/\/com.auth0.Auth0\/documentation\/Auth0\/MyAccountClient"},"doc://com.auth0.Auth0/documentation/Auth0/authorizeWithRequestUri(clientId:domain:)":{"title":"authorizeWithRequestUri(clientId:domain:)","fragments":[{"kind":"keyword","text":"func"},{"kind":"text","text":" "},{"kind":"identifier","text":"authorizeWithRequestUri"},{"kind":"text","text":"("},{"kind":"externalParam","text":"clientId"},{"kind":"text","text":": "},{"kind":"typeIdentifier","preciseIdentifier":"s:SS","text":"String"},{"kind":"text","text":", "},{"kind":"externalParam","text":"domain"},{"kind":"text","text":": "},{"kind":"typeIdentifier","preciseIdentifier":"s:SS","text":"String"},{"kind":"text","text":") -> "},{"kind":"typeIdentifier","preciseIdentifier":"s:5Auth07PARAuthP","text":"PARAuth"}],"url":"\/documentation\/auth0\/authorizewithrequesturi(clientid:domain:)","identifier":"doc:\/\/com.auth0.Auth0\/documentation\/Auth0\/authorizeWithRequestUri(clientId:domain:)","kind":"symbol","abstract":[{"type":"text","text":"PAR (Pushed Authorization Request) client for performing the browser authorization step of a PAR flow."}],"type":"topic","role":"symbol"},"doc://com.auth0.Auth0/documentation/Auth0/EmailEnrollmentChallenge":{"url":"\/documentation\/auth0\/emailenrollmentchallenge","kind":"symbol","navigatorTitle":[{"text":"EmailEnrollmentChallenge","kind":"identifier"}],"title":"EmailEnrollmentChallenge","role":"symbol","fragments":[{"text":"struct","kind":"keyword"},{"text":" ","kind":"text"},{"text":"EmailEnrollmentChallenge","kind":"identifier"}],"abstract":[{"text":"A Email enrollment challenge.","type":"text"}],"identifier":"doc:\/\/com.auth0.Auth0\/documentation\/Auth0\/EmailEnrollmentChallenge","type":"topic"},"doc://com.auth0.Auth0/documentation/Auth0/ManagementObject":{"kind":"symbol","title":"ManagementObject","fragments":[{"kind":"keyword","text":"typealias"},{"kind":"text","text":" "},{"kind":"identifier","text":"ManagementObject"}],"url":"\/documentation\/auth0\/managementobject","role":"symbol","navigatorTitle":[{"text":"ManagementObject","kind":"identifier"}],"deprecated":true,"identifier":"doc:\/\/com.auth0.Auth0\/documentation\/Auth0\/ManagementObject","abstract":[{"type":"text","text":"A dictionary containing a user profile."}],"type":"topic"},"doc://com.auth0.Auth0/documentation/Auth0/SSOCredentials":{"kind":"symbol","title":"SSOCredentials","fragments":[{"text":"struct","kind":"keyword"},{"text":" ","kind":"text"},{"text":"SSOCredentials","kind":"identifier"}],"url":"\/documentation\/auth0\/ssocredentials","role":"symbol","navigatorTitle":[{"text":"SSOCredentials","kind":"identifier"}],"identifier":"doc:\/\/com.auth0.Auth0\/documentation\/Auth0\/SSOCredentials","abstract":[{"type":"text","text":"Credentials obtained from Auth0 to perform web single sign-on (SSO)."}],"type":"topic"},"doc://com.auth0.Auth0/documentation/Auth0/TOTPEnrollmentChallenge":{"kind":"symbol","navigatorTitle":[{"text":"TOTPEnrollmentChallenge","kind":"identifier"}],"fragments":[{"text":"struct","kind":"keyword"},{"text":" ","kind":"text"},{"text":"TOTPEnrollmentChallenge","kind":"identifier"}],"identifier":"doc:\/\/com.auth0.Auth0\/documentation\/Auth0\/TOTPEnrollmentChallenge","title":"TOTPEnrollmentChallenge","abstract":[{"type":"text","text":"A TOTP enrollment challenge."}],"type":"topic","url":"\/documentation\/auth0\/totpenrollmentchallenge","role":"symbol"},"doc://com.auth0.Auth0/documentation/Auth0/CredentialsManagerError":{"url":"\/documentation\/auth0\/credentialsmanagererror","kind":"symbol","navigatorTitle":[{"text":"CredentialsManagerError","kind":"identifier"}],"title":"CredentialsManagerError","role":"symbol","fragments":[{"text":"struct","kind":"keyword"},{"text":" ","kind":"text"},{"text":"CredentialsManagerError","kind":"identifier"}],"abstract":[{"type":"text","text":"Represents an error during a Credentials Manager operation."}],"identifier":"doc:\/\/com.auth0.Auth0\/documentation\/Auth0\/CredentialsManagerError","type":"topic"},"doc://com.auth0.Auth0/documentation/Auth0/PasskeyCredential":{"fragments":[{"kind":"keyword","text":"struct"},{"kind":"text","text":" "},{"kind":"identifier","text":"PasskeyCredential"}],"abstract":[{"text":"A passkey credential.","type":"text"}],"identifier":"doc:\/\/com.auth0.Auth0\/documentation\/Auth0\/PasskeyCredential","title":"PasskeyCredential","url":"\/documentation\/auth0\/passkeycredential","type":"topic","kind":"symbol","role":"symbol","navigatorTitle":[{"kind":"identifier","text":"PasskeyCredential"}]},"doc://com.auth0.Auth0/documentation/Auth0/CredentialsManager":{"kind":"symbol","navigatorTitle":[{"text":"CredentialsManager","kind":"identifier"}],"fragments":[{"text":"struct","kind":"keyword"},{"text":" ","kind":"text"},{"text":"CredentialsManager","kind":"identifier"}],"identifier":"doc:\/\/com.auth0.Auth0\/documentation\/Auth0\/CredentialsManager","url":"\/documentation\/auth0\/credentialsmanager","type":"topic","abstract":[{"type":"text","text":"Credentials management utility for securely storing and retrieving the user’s credentials from the Keychain."}],"title":"CredentialsManager","role":"symbol"},"doc://com.auth0.Auth0/documentation/Auth0/RequestValidator":{"kind":"symbol","navigatorTitle":[{"kind":"identifier","text":"RequestValidator"}],"fragments":[{"kind":"keyword","text":"protocol"},{"kind":"text","text":" "},{"kind":"identifier","text":"RequestValidator"}],"identifier":"doc:\/\/com.auth0.Auth0\/documentation\/Auth0\/RequestValidator","title":"RequestValidator","abstract":[{"text":"Protocol for client-side validation of API request parameters before network calls.","type":"text"}],"type":"topic","url":"\/documentation\/auth0\/requestvalidator","role":"symbol"},"doc://com.auth0.Auth0/documentation/Auth0/AuthorizationCode":{"kind":"symbol","navigatorTitle":[{"kind":"identifier","text":"AuthorizationCode"}],"fragments":[{"kind":"keyword","text":"struct"},{"kind":"text","text":" "},{"kind":"identifier","text":"AuthorizationCode"}],"identifier":"doc:\/\/com.auth0.Auth0\/documentation\/Auth0\/AuthorizationCode","title":"AuthorizationCode","abstract":[{"text":"The result of a PAR (Pushed Authorization Request) authorization flow.","type":"text"}],"type":"topic","url":"\/documentation\/auth0\/authorizationcode","role":"symbol"},"doc://com.auth0.Auth0/documentation/Auth0/ManagementResult":{"url":"\/documentation\/auth0\/managementresult","kind":"symbol","navigatorTitle":[{"text":"ManagementResult","kind":"identifier"}],"deprecated":true,"title":"ManagementResult","role":"symbol","fragments":[{"text":"typealias","kind":"keyword"},{"text":" ","kind":"text"},{"text":"ManagementResult","kind":"identifier"}],"abstract":[{"code":"Result","type":"codeVoice"},{"text":" wrapper for Management API operations.","type":"text"}],"type":"topic","identifier":"doc:\/\/com.auth0.Auth0\/documentation\/Auth0\/ManagementResult"},"doc://com.auth0.Auth0/documentation/Auth0/APICredentials":{"navigatorTitle":[{"text":"APICredentials","kind":"identifier"}],"role":"symbol","url":"\/documentation\/auth0\/apicredentials","title":"APICredentials","type":"topic","fragments":[{"text":"struct","kind":"keyword"},{"text":" ","kind":"text"},{"text":"APICredentials","kind":"identifier"}],"identifier":"doc:\/\/com.auth0.Auth0\/documentation\/Auth0\/APICredentials","kind":"symbol","abstract":[{"type":"text","text":"User’s credentials obtained from Auth0 for a specific API as the result of exchanging a refresh token."}]},"doc://com.auth0.Auth0/documentation/Auth0/WebAuthResult":{"kind":"symbol","navigatorTitle":[{"text":"WebAuthResult","kind":"identifier"}],"fragments":[{"text":"typealias","kind":"keyword"},{"text":" ","kind":"text"},{"text":"WebAuthResult","kind":"identifier"}],"identifier":"doc:\/\/com.auth0.Auth0\/documentation\/Auth0\/WebAuthResult","url":"\/documentation\/auth0\/webauthresult","abstract":[{"code":"Result","type":"codeVoice"},{"text":" wrapper for Web Auth operations.","type":"text"}],"title":"WebAuthResult","type":"topic","role":"symbol"},"doc://com.auth0.Auth0/documentation/Auth0/AuthenticationMethod":{"kind":"symbol","title":"AuthenticationMethod","fragments":[{"kind":"keyword","text":"struct"},{"kind":"text","text":" "},{"kind":"identifier","text":"AuthenticationMethod"}],"url":"\/documentation\/auth0\/authenticationmethod","role":"symbol","navigatorTitle":[{"kind":"identifier","text":"AuthenticationMethod"}],"identifier":"doc:\/\/com.auth0.Auth0\/documentation\/Auth0\/AuthenticationMethod","abstract":[],"type":"topic"},"doc://com.auth0.Auth0/documentation/Auth0/SimpleKeychain":{"role":"collection","url":"\/documentation\/auth0\/simplekeychain","title":"SimpleKeychain","type":"topic","identifier":"doc:\/\/com.auth0.Auth0\/documentation\/Auth0\/SimpleKeychain","kind":"symbol","abstract":[]},"doc://com.auth0.Auth0/documentation/Auth0/MfaChallengeError":{"kind":"symbol","title":"MfaChallengeError","fragments":[{"kind":"keyword","text":"struct"},{"kind":"text","text":" "},{"kind":"identifier","text":"MfaChallengeError"}],"url":"\/documentation\/auth0\/mfachallengeerror","role":"symbol","navigatorTitle":[{"kind":"identifier","text":"MfaChallengeError"}],"identifier":"doc:\/\/com.auth0.Auth0\/documentation\/Auth0\/MfaChallengeError","abstract":[{"type":"text","text":"Error raised when initiating an MFA challenge fails."}],"type":"topic"},"doc://com.auth0.Auth0/documentation/Auth0/MyAccountResult":{"title":"MyAccountResult","fragments":[{"text":"typealias","kind":"keyword"},{"text":" ","kind":"text"},{"text":"MyAccountResult","kind":"identifier"}],"url":"\/documentation\/auth0\/myaccountresult","identifier":"doc:\/\/com.auth0.Auth0\/documentation\/Auth0\/MyAccountResult","kind":"symbol","abstract":[{"code":"Result","type":"codeVoice"},{"text":" wrapper for My Account API operations.","type":"text"}],"type":"topic","role":"symbol","navigatorTitle":[{"text":"MyAccountResult","kind":"identifier"}]},"doc://com.auth0.Auth0/documentation/Auth0":{"title":"Auth0","url":"\/documentation\/auth0","identifier":"doc:\/\/com.auth0.Auth0\/documentation\/Auth0","abstract":[{"type":"text","text":"SDK for Apple platforms."}],"kind":"symbol","type":"topic","role":"collection"},"doc://com.auth0.Auth0/documentation/Auth0/AuthenticationMethodType":{"navigatorTitle":[{"kind":"identifier","text":"AuthenticationMethodType"}],"role":"symbol","url":"\/documentation\/auth0\/authenticationmethodtype","title":"AuthenticationMethodType","type":"topic","fragments":[{"kind":"keyword","text":"enum"},{"kind":"text","text":" "},{"kind":"identifier","text":"AuthenticationMethodType"}],"identifier":"doc:\/\/com.auth0.Auth0\/documentation\/Auth0\/AuthenticationMethodType","kind":"symbol","abstract":[{"type":"text","text":"The type of authentication method to filter by when listing authentication methods."}]},"doc://com.auth0.Auth0/documentation/Auth0/MyAccountError":{"kind":"symbol","navigatorTitle":[{"text":"MyAccountError","kind":"identifier"}],"fragments":[{"text":"struct","kind":"keyword"},{"text":" ","kind":"text"},{"text":"MyAccountError","kind":"identifier"}],"identifier":"doc:\/\/com.auth0.Auth0\/documentation\/Auth0\/MyAccountError","title":"MyAccountError","type":"topic","url":"\/documentation\/auth0\/myaccounterror","abstract":[{"type":"text","text":"Represents an error during a request to the Auth0 My Account API."}],"role":"symbol"},"doc://com.auth0.Auth0/documentation/Auth0/PARAuth":{"url":"\/documentation\/auth0\/parauth","kind":"symbol","navigatorTitle":[{"kind":"identifier","text":"PARAuth"}],"title":"PARAuth","role":"symbol","fragments":[{"kind":"keyword","text":"protocol"},{"kind":"text","text":" "},{"kind":"identifier","text":"PARAuth"}],"abstract":[{"type":"text","text":"Web-based PAR (Pushed Authorization Request) authorization."}],"type":"topic","identifier":"doc:\/\/com.auth0.Auth0\/documentation\/Auth0\/PARAuth"},"https://auth0.com/docs/api/management/v2":{"title":"Management API v2","identifier":"https:\/\/auth0.com\/docs\/api\/management\/v2","url":"https:\/\/auth0.com\/docs\/api\/management\/v2","type":"link","titleInlineContent":[{"text":"Management API v2","type":"text"}]},"doc://com.auth0.Auth0/documentation/Auth0/PushMFAEnrollmentChallenge":{"navigatorTitle":[{"text":"PushMFAEnrollmentChallenge","kind":"identifier"}],"role":"symbol","url":"\/documentation\/auth0\/pushmfaenrollmentchallenge","title":"PushMFAEnrollmentChallenge","type":"topic","fragments":[{"text":"struct","kind":"keyword"},{"text":" ","kind":"text"},{"text":"PushMFAEnrollmentChallenge","kind":"identifier"}],"identifier":"doc:\/\/com.auth0.Auth0\/documentation\/Auth0\/PushMFAEnrollmentChallenge","kind":"symbol","abstract":[{"text":"Represents the response from enrolling a push notification authenticator (Auth0 Guardian).","type":"text"}]},"doc://com.auth0.Auth0/documentation/Auth0/mfa(clientId:domain:session:)":{"url":"\/documentation\/auth0\/mfa(clientid:domain:session:)","kind":"symbol","title":"mfa(clientId:domain:session:)","role":"symbol","fragments":[{"text":"func","kind":"keyword"},{"text":" ","kind":"text"},{"text":"mfa","kind":"identifier"},{"text":"(","kind":"text"},{"text":"clientId","kind":"externalParam"},{"kind":"text","text":": "},{"kind":"typeIdentifier","preciseIdentifier":"s:SS","text":"String"},{"kind":"text","text":", "},{"kind":"externalParam","text":"domain"},{"kind":"text","text":": "},{"preciseIdentifier":"s:SS","kind":"typeIdentifier","text":"String"},{"kind":"text","text":", "},{"kind":"externalParam","text":"session"},{"text":": ","kind":"text"},{"text":"URLSession","preciseIdentifier":"c:objc(cs)NSURLSession","kind":"typeIdentifier"},{"text":") -> ","kind":"text"},{"text":"MFAClient","preciseIdentifier":"s:5Auth09MFAClientP","kind":"typeIdentifier"}],"abstract":[{"text":"Multi-Factor Authentication (MFA) client for performing MFA operations during authentication flows.","type":"text"}],"identifier":"doc:\/\/com.auth0.Auth0\/documentation\/Auth0\/mfa(clientId:domain:session:)","type":"topic"},"doc://com.auth0.Auth0/documentation/Auth0/Factors":{"url":"\/documentation\/auth0\/factors","kind":"symbol","navigatorTitle":[{"text":"Factors","kind":"identifier"}],"title":"Factors","role":"symbol","fragments":[{"text":"struct","kind":"keyword"},{"text":" ","kind":"text"},{"text":"Factors","kind":"identifier"}],"abstract":[{"text":"List of factors enabled for the Auth0 tenant and available for enrollment by this user.","type":"text"}],"type":"topic","identifier":"doc:\/\/com.auth0.Auth0\/documentation\/Auth0\/Factors"},"doc://com.auth0.Auth0/documentation/Auth0/WebAuthentication":{"url":"\/documentation\/auth0\/webauthentication","kind":"symbol","navigatorTitle":[{"kind":"identifier","text":"WebAuthentication"}],"title":"WebAuthentication","role":"symbol","fragments":[{"kind":"keyword","text":"struct"},{"kind":"text","text":" "},{"kind":"identifier","text":"WebAuthentication"}],"abstract":[{"type":"text","text":"Utility methods needed when using a custom Web Auth provider."}],"identifier":"doc:\/\/com.auth0.Auth0\/documentation\/Auth0\/WebAuthentication","type":"topic"},"doc://com.auth0.Auth0/documentation/Auth0/ManagementError":{"deprecated":true,"kind":"symbol","navigatorTitle":[{"text":"ManagementError","kind":"identifier"}],"fragments":[{"text":"struct","kind":"keyword"},{"text":" ","kind":"text"},{"text":"ManagementError","kind":"identifier"}],"identifier":"doc:\/\/com.auth0.Auth0\/documentation\/Auth0\/ManagementError","title":"ManagementError","type":"topic","url":"\/documentation\/auth0\/managementerror","abstract":[{"text":"Represents an error during a request to the Auth0 Management API v2.","type":"text"}],"role":"symbol"},"doc://com.auth0.Auth0/documentation/Auth0/CredentialsManagerResult":{"title":"CredentialsManagerResult","fragments":[{"text":"typealias","kind":"keyword"},{"text":" ","kind":"text"},{"text":"CredentialsManagerResult","kind":"identifier"}],"url":"\/documentation\/auth0\/credentialsmanagerresult","identifier":"doc:\/\/com.auth0.Auth0\/documentation\/Auth0\/CredentialsManagerResult","kind":"symbol","type":"topic","abstract":[{"type":"codeVoice","code":"Result"},{"type":"text","text":" wrapper for Credentials Manager operations."}],"role":"symbol","navigatorTitle":[{"text":"CredentialsManagerResult","kind":"identifier"}]},"doc://com.auth0.Auth0/documentation/Auth0/WebAuthProviderCallback":{"kind":"symbol","title":"WebAuthProviderCallback","fragments":[{"text":"typealias","kind":"keyword"},{"text":" ","kind":"text"},{"text":"WebAuthProviderCallback","kind":"identifier"}],"url":"\/documentation\/auth0\/webauthprovidercallback","role":"symbol","navigatorTitle":[{"text":"WebAuthProviderCallback","kind":"identifier"}],"identifier":"doc:\/\/com.auth0.Auth0\/documentation\/Auth0\/WebAuthProviderCallback","abstract":[{"text":"Callback invoked by the ","type":"text"},{"type":"reference","identifier":"doc:\/\/com.auth0.Auth0\/documentation\/Auth0\/WebAuthUserAgent","isActive":true},{"text":" when the web-based operation concludes.","type":"text"}],"type":"topic"},"https://developer.apple.com/documentation/authenticationservices/asauthorizationcontrollerdelegate":{"url":"https:\/\/developer.apple.com\/documentation\/authenticationservices\/asauthorizationcontrollerdelegate","titleInlineContent":[{"type":"codeVoice","code":"ASAuthorizationControllerDelegate"}],"identifier":"https:\/\/developer.apple.com\/documentation\/authenticationservices\/asauthorizationcontrollerdelegate","title":"ASAuthorizationControllerDelegate","type":"link"},"doc://com.auth0.Auth0/documentation/Auth0/defaultScope":{"fragments":[{"kind":"keyword","text":"let"},{"text":" ","kind":"text"},{"text":"defaultScope","kind":"identifier"},{"text":": ","kind":"text"},{"preciseIdentifier":"s:SS","text":"String","kind":"typeIdentifier"}],"abstract":[{"text":"Default scope value used across Auth0.swift. Equals to ","type":"text"},{"type":"codeVoice","code":"openid profile email"},{"text":".","type":"text"}],"identifier":"doc:\/\/com.auth0.Auth0\/documentation\/Auth0\/defaultScope","title":"defaultScope","url":"\/documentation\/auth0\/defaultscope","type":"topic","kind":"symbol","role":"symbol"},"doc://com.auth0.Auth0/documentation/Auth0/NewPasskey":{"navigatorTitle":[{"text":"NewPasskey","kind":"identifier"}],"role":"symbol","url":"\/documentation\/auth0\/newpasskey","title":"NewPasskey","type":"topic","fragments":[{"text":"protocol","kind":"keyword"},{"text":" ","kind":"text"},{"text":"NewPasskey","kind":"identifier"}],"identifier":"doc:\/\/com.auth0.Auth0\/documentation\/Auth0\/NewPasskey","kind":"symbol","abstract":[{"type":"text","text":"The signup passkey credential obtained from the "},{"identifier":"https:\/\/developer.apple.com\/documentation\/authenticationservices\/asauthorizationcontrollerdelegate","type":"reference","isActive":true},{"type":"text","text":" delegate."},{"type":"text","text":" "},{"type":"text","text":"Contains the subset of relevant properties from "},{"identifier":"https:\/\/developer.apple.com\/documentation\/authenticationservices\/asauthorizationplatformpublickeycredentialregistration","type":"reference","isActive":true},{"type":"text","text":"."}]},"doc://com.auth0.Auth0/documentation/Auth0/Credentials":{"title":"Credentials","navigatorTitle":[{"kind":"identifier","text":"Credentials"}],"kind":"symbol","type":"topic","role":"symbol","identifier":"doc:\/\/com.auth0.Auth0\/documentation\/Auth0\/Credentials","abstract":[{"text":"User’s credentials obtained from Auth0.","type":"text"}],"url":"\/documentation\/auth0\/credentials","fragments":[{"text":"class","kind":"keyword"},{"kind":"text","text":" "},{"text":"Credentials","kind":"identifier"}]},"doc://com.auth0.Auth0/documentation/Auth0/PasskeyAuthenticationMethod":{"title":"PasskeyAuthenticationMethod","fragments":[{"text":"struct","kind":"keyword"},{"text":" ","kind":"text"},{"text":"PasskeyAuthenticationMethod","kind":"identifier"}],"url":"\/documentation\/auth0\/passkeyauthenticationmethod","identifier":"doc:\/\/com.auth0.Auth0\/documentation\/Auth0\/PasskeyAuthenticationMethod","abstract":[{"type":"text","text":"A passkey authentication method."}],"type":"topic","kind":"symbol","role":"symbol","navigatorTitle":[{"text":"PasskeyAuthenticationMethod","kind":"identifier"}]},"doc://com.auth0.Auth0/documentation/Auth0/SignupPasskey":{"url":"\/documentation\/auth0\/signuppasskey","kind":"symbol","navigatorTitle":[{"text":"SignupPasskey","kind":"identifier"}],"title":"SignupPasskey","role":"symbol","fragments":[{"text":"protocol","kind":"keyword"},{"text":" ","kind":"text"},{"text":"SignupPasskey","kind":"identifier"}],"abstract":[{"type":"text","text":"The signup passkey credential obtained from the "},{"type":"reference","isActive":true,"identifier":"https:\/\/developer.apple.com\/documentation\/authenticationservices\/asauthorizationcontrollerdelegate"},{"type":"text","text":" delegate."},{"type":"text","text":" "},{"type":"text","text":"Contains the subset of relevant properties from "},{"type":"reference","isActive":true,"identifier":"https:\/\/developer.apple.com\/documentation\/authenticationservices\/asauthorizationplatformpublickeycredentialregistration"},{"type":"text","text":"."}],"identifier":"doc:\/\/com.auth0.Auth0\/documentation\/Auth0\/SignupPasskey","type":"topic"},"doc://com.auth0.Auth0/documentation/Auth0/OTPMFAEnrollmentChallenge":{"url":"\/documentation\/auth0\/otpmfaenrollmentchallenge","kind":"symbol","navigatorTitle":[{"text":"OTPMFAEnrollmentChallenge","kind":"identifier"}],"title":"OTPMFAEnrollmentChallenge","role":"symbol","fragments":[{"text":"struct","kind":"keyword"},{"text":" ","kind":"text"},{"text":"OTPMFAEnrollmentChallenge","kind":"identifier"}],"abstract":[{"type":"text","text":"Represents the response from enrolling a TOTP (Time-based One-Time Password) authenticator."}],"type":"topic","identifier":"doc:\/\/com.auth0.Auth0\/documentation\/Auth0\/OTPMFAEnrollmentChallenge"},"https://auth0.com/docs/authenticate/login/auth0-universal-login":{"type":"link","title":"Universal Login","titleInlineContent":[{"type":"text","text":"Universal Login"}],"identifier":"https:\/\/auth0.com\/docs\/authenticate\/login\/auth0-universal-login","url":"https:\/\/auth0.com\/docs\/authenticate\/login\/auth0-universal-login"},"doc://com.auth0.Auth0/documentation/Auth0/MFAEnrollmentChallenge":{"kind":"symbol","navigatorTitle":[{"kind":"identifier","text":"MFAEnrollmentChallenge"}],"fragments":[{"kind":"keyword","text":"struct"},{"kind":"text","text":" "},{"kind":"identifier","text":"MFAEnrollmentChallenge"}],"identifier":"doc:\/\/com.auth0.Auth0\/documentation\/Auth0\/MFAEnrollmentChallenge","title":"MFAEnrollmentChallenge","type":"topic","url":"\/documentation\/auth0\/mfaenrollmentchallenge","abstract":[{"type":"text","text":"Represents the response from enrolling an MFA factor."}],"role":"symbol"},"doc://com.auth0.Auth0/documentation/Auth0/Foundation":{"role":"collection","url":"\/documentation\/auth0\/foundation","title":"Foundation","type":"topic","identifier":"doc:\/\/com.auth0.Auth0\/documentation\/Auth0\/Foundation","kind":"symbol","abstract":[]}}}